Workbook

Sheet Assumptions
A1: CPP-at-61 Redirect vs. Defer — Assumptions
A3: Real discount rate / real return | B3: 0.03 | C3: CPI-indexed CPP held flat in real $ (file 11)
A4: Marginal tax rate — now (working) | B4: 0.43 | C4: Alberta ~$200k+ band, 2026 (confirm vs NOA)
A5: Marginal tax rate — retirement | B5: 0.33 | C5: On RRSP/RRIF withdrawals at ~$94k income
A6: Current age | B6: 61 | C6: Born Feb 1, 1965 (file 01)
A7: Planning-to age | B7: 90 | C7: Base case (file 01)
A8: RRSP unused room | B8: 89071 | C8: File 08 (Alec)
A9: CPP annual — start age 61 | B9: 13315.56 | C9: Source: MSCA estimate (file 07)
A10: CPP annual — start age 65 | B10: 18091.8 | C10: Source: MSCA estimate (file 07)
A11: CPP annual — start age 70 | B11: 25690.32 | C11: Source: MSCA estimate (file 07)
A12: Volvo loan freed cash/yr (from ~Nov 2026) | B12: 10267 | C12: File 05 — frees ~0.5 yr from now
A13: Insurance reduction/yr (from ~2027) | B13: 1800 | C13: File 05 — son off auto, ~1 yr out
A14: Bolt loan freed cash/yr (from ~2031) | B14: 9509 | C14: File 05 — ~4.5 yr out
... A17: Years to retirement — 2032 path | B17: 5.6 | C17: mid-2026 to Feb 2032
A19: Blue = input you can change. Yellow = key assumption.

Sheet CPP value
A1: Lifetime CPP value by start age (real $, PV at current age)
A3: Age | B3: Years from now | C3: Discount factor | D3: CPP if start 61 | E3: CPP if start 65 | F3: CPP if start 70 | G3: PV start 61 | H3: PV start 65 | I3: PV start 70 | J3: Cum. real start 61 | K3: Cum. real start 65 | L3: Cum. real start 70
A4: 61 | B4: =A4-Assumptions!$B$6 -> 0 | C4: =1/(1+Assumptions!$B$3)^B4 -> 1 | D4: =IF(AND(A4>=61,A4<=Assumptions!$B$7),Assumptions!$B$9,0) -> 13315.56 | E4: =IF(AND(A4>=65,A4<=Assumptions!$B$7),Assumptions!$B$10,0) -> 0 | F4: =IF(AND(A4>=70,A4<=Assumptions!$B$7),Assumptions!$B$11,0) -> 0 | G4: =D4*C4 -> 13315.56 | H4: =E4*C4 -> 0 | I4: =F4*C4 -> 0 | J4: =D4 -> 13315.56 | K4: =E4 -> 0 | L4: =F4 -> 0
A5: 62 | B5: =A5-Assumptions!$B$6 -> 1 | C5: =1/(1+Assumptions!$B$3)^B5 -> 0.97087379 | D5: =IF(AND(A5>=61,A5<=Assumptions!$B$7),Assumptions!$B$9,0) -> 13315.56 | E5: =IF(AND(A5>=65,A5<=Assumptions!$B$7),Assumptions!$B$10,0) -> 0 | F5: =IF(AND(A5>=70,A5<=Assumptions!$B$7),Assumptions!$B$11,0) -> 0 | G5: =D5*C5 -> 12927.728 | H5: =E5*C5 -> 0 | I5: =F5*C5 -> 0 | J5: =IF(A5=61,D5,J4+D5) -> 26631.12 | K5: =IF(A5=61,E5,K4+E5) -> 0 | L5: =IF(A5=61,F5,L4+F5) -> 0
A6: 63 | B6: =A6-Assumptions!$B$6 -> 2 | C6: =1/(1+Assumptions!$B$3)^B6 -> 0.94259591 | D6: =IF(AND(A6>=61,A6<=Assumptions!$B$7),Assumptions!$B$9,0) -> 13315.56 | E6: =IF(AND(A6>=65,A6<=Assumptions!$B$7),Assumptions!$B$10,0) -> 0 | F6: =IF(AND(A6>=70,A6<=Assumptions!$B$7),Assumptions!$B$11,0) -> 0 | G6: =D6*C6 -> 12551.192 | H6: =E6*C6 -> 0 | I6: =F6*C6 -> 0 | J6: =IF(A6=61,D6,J5+D6) -> 39946.68 | K6: =IF(A6=61,E6,K5+E6) -> 0 | L6: =IF(A6=61,F6,L5+F6) -> 0
A7: 64 | B7: =A7-Assumptions!$B$6 -> 3 | C7: =1/(1+Assumptions!$B$3)^B7 -> 0.91514166 | D7: =IF(AND(A7>=61,A7<=Assumptions!$B$7),Assumptions!$B$9,0) -> 13315.56 | E7: =IF(AND(A7>=65,A7<=Assumptions!$B$7),Assumptions!$B$10,0) -> 0 | F7: =IF(AND(A7>=70,A7<=Assumptions!$B$7),Assumptions!$B$11,0) -> 0 | G7: =D7*C7 -> 12185.624 | H7: =E7*C7 -> 0 | I7: =F7*C7 -> 0 | J7: =IF(A7=61,D7,J6+D7) -> 53262.24 | K7: =IF(A7=61,E7,K6+E7) -> 0 | L7: =IF(A7=61,F7,L6+F7) -> 0
A8: 65 | B8: =A8-Assumptions!$B$6 -> 4 | C8: =1/(1+Assumptions!$B$3)^B8 -> 0.88848705 | D8: =IF(AND(A8>=61,A8<=Assumptions!$B$7),Assumptions!$B$9,0) -> 13315.56 | E8: =IF(AND(A8>=65,A8<=Assumptions!$B$7),Assumptions!$B$10,0) -> 18091.8 | F8: =IF(AND(A8>=70,A8<=Assumptions!$B$7),Assumptions!$B$11,0) -> 0 | G8: =D8*C8 -> 11830.703 | H8: =E8*C8 -> 16074.33 | I8: =F8*C8 -> 0 | J8: =IF(A8=61,D8,J7+D8) -> 66577.8 | K8: =IF(A8=61,E8,K7+E8) -> 18091.8 | L8: =IF(A8=61,F8,L7+F8) -> 0
A9: 66 | B9: =A9-Assumptions!$B$6 -> 5 | C9: =1/(1+Assumptions!$B$3)^B9 -> 0.86260878 | D9: =IF(AND(A9>=61,A9<=Assumptions!$B$7),Assumptions!$B$9,0) -> 13315.56 | E9: =IF(AND(A9>=65,A9<=Assumptions!$B$7),Assumptions!$B$10,0) -> 18091.8 | F9: =IF(AND(A9>=70,A9<=Assumptions!$B$7),Assumptions!$B$11,0) -> 0 | G9: =D9*C9 -> 11486.119 | H9: =E9*C9 -> 15606.146 | I9: =F9*C9 -> 0 | J9: =IF(A9=61,D9,J8+D9) -> 79893.36 | K9: =IF(A9=61,E9,K8+E9) -> 36183.6 | L9: =IF(A9=61,F9,L8+F9) -> 0
A10: 67 | B10: =A10-Assumptions!$B$6 -> 6 | C10: =1/(1+Assumptions!$B$3)^B10 -> 0.83748426 | D10: =IF(AND(A10>=61,A10<=Assumptions!$B$7),Assumptions!$B$9,0) -> 13315.56 | E10: =IF(AND(A10>=65,A10<=Assumptions!$B$7),Assumptions!$B$10,0) -> 18091.8 | F10: =IF(AND(A10>=70,A10<=Assumptions!$B$7),Assumptions!$B$11,0) -> 0 | G10: =D10*C10 -> 11151.572 | H10: =E10*C10 -> 15151.598 | I10: =F10*C10 -> 0 | J10: =IF(A10=61,D10,J9+D10) -> 93208.92 | K10: =IF(A10=61,E10,K9+E10) -> 54275.4 | L10: =IF(A10=61,F10,L9+F10) -> 0
A11: 68 | B11: =A11-Assumptions!$B$6 -> 7 | C11: =1/(1+Assumptions!$B$3)^B11 -> 0.81309151 | D11: =IF(AND(A11>=61,A11<=Assumptions!$B$7),Assumptions!$B$9,0) -> 13315.56 | E11: =IF(AND(A11>=65,A11<=Assumptions!$B$7),Assumptions!$B$10,0) -> 18091.8 | F11: =IF(AND(A11>=70,A11<=Assumptions!$B$7),Assumptions!$B$11,0) -> 0 | G11: =D11*C11 -> 10826.769 | H11: =E11*C11 -> 14710.289 | I11: =F11*C11 -> 0 | J11: =IF(A11=61,D11,J10+D11) -> 106524.48 | K11: =IF(A11=61,E11,K10+E11) -> 72367.2 | L11: =IF(A11=61,F11,L10+F11) -> 0
A12: 69 | B12: =A12-Assumptions!$B$6 -> 8 | C12: =1/(1+Assumptions!$B$3)^B12 -> 0.78940923 | D12: =IF(AND(A12>=61,A12<=Assumptions!$B$7),Assumptions!$B$9,0) -> 13315.56 | E12: =IF(AND(A12>=65,A12<=Assumptions!$B$7),Assumptions!$B$10,0) -> 18091.8 | F12: =IF(AND(A12>=70,A12<=Assumptions!$B$7),Assumptions!$B$11,0) -> 0 | G12: =D12*C12 -> 10511.426 | H12: =E12*C12 -> 14281.834 | I12: =F12*C12 -> 0 | J12: =IF(A12=61,D12,J11+D12) -> 119840.04 | K12: =IF(A12=61,E12,K11+E12) -> 90459 | L12: =IF(A12=61,F12,L11+F12) -> 0
A13: 70 | B13: =A13-Assumptions!$B$6 -> 9 | C13: =1/(1+Assumptions!$B$3)^B13 -> 0.76641673 | D13: =IF(AND(A13>=61,A13<=Assumptions!$B$7),Assumptions!$B$9,0) -> 13315.56 | E13: =IF(AND(A13>=65,A13<=Assumptions!$B$7),Assumptions!$B$10,0) -> 18091.8 | F13: =IF(AND(A13>=70,A13<=Assumptions!$B$7),Assumptions!$B$11,0) -> 25690.32 | G13: =D13*C13 -> 10205.268 | H13: =E13*C13 -> 13865.858 | I13: =F13*C13 -> 19689.491 | J13: =IF(A13=61,D13,J12+D13) -> 133155.6 | K13: =IF(A13=61,E13,K12+E13) -> 108550.8 | L13: =IF(A13=61,F13,L12+F13) -> 25690.32
A14: 71 | B14: =A14-Assumptions!$B$6 -> 10 | C14: =1/(1+Assumptions!$B$3)^B14 -> 0.74409391 | D14: =IF(AND(A14>=61,A14<=Assumptions!$B$7),Assumptions!$B$9,0) -> 13315.56 | E14: =IF(AND(A14>=65,A14<=Assumptions!$B$7),Assumptions!$B$10,0) -> 18091.8 | F14: =IF(AND(A14>=70,A14<=Assumptions!$B$7),Assumptions!$B$11,0) -> 25690.32 | G14: =D14*C14 -> 9908.0272 | H14: =E14*C14 -> 13461.998 | I14: =F14*C14 -> 19116.011 | J14: =IF(A14=61,D14,J13+D14) -> 146471.16 | K14: =IF(A14=61,E14,K13+E14) -> 126642.6 | L14: =IF(A14=61,F14,L13+F14) -> 51380.64
A15: 72 | B15: =A15-Assumptions!$B$6 -> 11 | C15: =1/(1+Assumptions!$B$3)^B15 -> 0.72242128 | D15: =IF(AND(A15>=61,A15<=Assumptions!$B$7),Assumptions!$B$9,0) -> 13315.56 | E15: =IF(AND(A15>=65,A15<=Assumptions!$B$7),Assumptions!$B$10,0) -> 18091.8 | F15: =IF(AND(A15>=70,A15<=Assumptions!$B$7),Assumptions!$B$11,0) -> 25690.32 | G15: =D15*C15 -> 9619.4439 | H15: =E15*C15 -> 13069.901 | I15: =F15*C15 -> 18559.234 | J15: =IF(A15=61,D15,J14+D15) -> 159786.72 | K15: =IF(A15=61,E15,K14+E15) -> 144734.4 | L15: =IF(A15=61,F15,L14+F15) -> 77070.96
A16: 73 | B16: =A16-Assumptions!$B$6 -> 12 | C16: =1/(1+Assumptions!$B$3)^B16 -> 0.70137988 | D16: =IF(AND(A16>=61,A16<=Assumptions!$B$7),Assumptions!$B$9,0) -> 13315.56 | E16: =IF(AND(A16>=65,A16<=Assumptions!$B$7),Assumptions!$B$10,0) -> 18091.8 | F16: =IF(AND(A16>=70,A16<=Assumptions!$B$7),Assumptions!$B$11,0) -> 25690.32 | G16: =D16*C16 -> 9339.2659 | H16: =E16*C16 -> 12689.225 | I16: =F16*C16 -> 18018.674 | J16: =IF(A16=61,D16,J15+D16) -> 173102.28 | K16: =IF(A16=61,E16,K15+E16) -> 162826.2 | L16: =IF(A16=61,F16,L15+F16) -> 102761.28
... A38: 95 | B38: =A38-Assumptions!$B$6 -> 34 | C38: =1/(1+Assumptions!$B$3)^B38 -> 0.3660449 | D38: =IF(AND(A38>=61,A38<=Assumptions!$B$7),Assumptions!$B$9,0) -> 0 | E38: =IF(AND(A38>=65,A38<=Assumptions!$B$7),Assumptions!$B$10,0) -> 0 | F38: =IF(AND(A38>=70,A38<=Assumptions!$B$7),Assumptions!$B$11,0) -> 0 | G38: =D38*C38 -> 0 | H38: =E38*C38 -> 0 | I38: =F38*C38 -> 0 | J38: =IF(A38=61,D38,J37+D38) -> 399466.8 | K38: =IF(A38=61,E38,K37+E38) -> 470386.8 | L38: =IF(A38=61,F38,L37+F38) -> 539496.72
A39: PV total | G39: =SUM(G4:G38) -> 268820.58 | H39: =SUM(H4:H38) -> 295979.01 | I39: =SUM(I4:I38) -> 312619.4

Sheet RRSP room fill
A1: Filling RRSP room from freed loan cash (no early CPP)
A3: Source | B3: By 2030 retire | C3: By 2032 retire
A4: Volvo freed (from ~Nov 2026) | B4: =Assumptions!$B$12*MAX(0,Assumptions!$B$16-0.5) -> 31827.7 | C4: =Assumptions!$B$12*MAX(0,Assumptions!$B$17-0.5) -> 52361.7
A5: Insurance reduction (~2027) | B5: =Assumptions!$B$13*MAX(0,Assumptions!$B$16-1) -> 4680 | C5: =Assumptions!$B$13*MAX(0,Assumptions!$B$17-1) -> 8280
A6: Bolt freed (~2031) | B6: =Assumptions!$B$14*MAX(0,Assumptions!$B$16-4.5) -> 0 | C6: =Assumptions!$B$14*MAX(0,Assumptions!$B$17-4.5) -> 10459.9
A7: Existing voluntary RRSP | B7: =Assumptions!$B$15*Assumptions!$B$16 -> 7394.4 | C7: =Assumptions!$B$15*Assumptions!$B$17 -> 11502.4
A8: Total filled from freed cash | B8: =SUM(B4:B7) -> 43902.1 | C8: =SUM(C4:C7) -> 82604
A9: RRSP room left UNFILLED | B9: =MAX(0,Assumptions!$B$8-B8) -> 45168.9 | C9: =MAX(0,Assumptions!$B$8-C8) -> 6467

Sheet Decision
A1: The trade: take CPP at 61 to fill room vs. defer CPP
A3: PV of CPP — start 61 | B3: ='CPP value'!$G$39 -> 268820.58
A4: PV of CPP — start 65 | B4: ='CPP value'!$H$39 -> 295979.01
A5: PV of CPP — start 70 | B5: ='CPP value'!$I$39 -> 312619.4
A6: Deferral gain: 65 vs 61 | B6: ='CPP value'!$H$39-'CPP value'!$G$39 -> 27158.433 | C6: Cost of taking CPP at 61 instead of 65
A7: Deferral gain: 70 vs 61 | B7: ='CPP value'!$I$39-'CPP value'!$G$39 -> 43798.822
A9: 2030 path — should you fill the gap with early CPP?
A10: RRSP room left unfilled (2030) | B10: ='RRSP room fill'!$B$9 -> 45168.9
A11: Deduction capture if filled (bracket spread) | B11: ='RRSP room fill'!$B$9*(Assumptions!$B$4-Assumptions!$B$5) -> 4516.89 | C11: Deduct now @43%, withdraw @33% = ~10%
A12: Less: CPP reduction cost (PV, 65 vs 61) | B12: =-('CPP value'!$H$39-'CPP value'!$G$39) -> -27158.433
A13: NET of using early CPP to fill room | B13: =B11+B12 -> -22641.543 | C13: Negative = early CPP loses
A15: 2032 path
A16: RRSP room left unfilled (2032) | B16: ='RRSP room fill'!$C$9 -> 6467 | C16: Freed loan cash nearly fills it — no need to touch CPP
A18: VERDICT
A19: =IF(B13<0,"Don't take CPP at 61 to fund RRSP: filling the gap nets "&TEXT(B13,"$#,##0")&" — the deduction saved is dwarfed by the CPP reduction. Defer CPP; fund room from freed loan cash.","Re-check: early CPP fill is net positive under current inputs.") -> Don't take CPP at 61 to fund RRSP: filling the gap nets -$22,642 — the deduction saved is dwarfed by the CPP reduction. Defer CPP; fund room from freed loan cash.
