Workbook

Sheet Loan Calculator
A1: CAR LOAN INPUTS | D1: RESULTS SUMMARY
A2: Current Loan Balance | B2: 36890 | D2: Starting Balance After Lump Sum #1 | E2: =B2-B10 -> 27390
A3: Annual Interest Rate | B3: 0.06 | D3: Total Periods to Payoff | E3: =Amortization!M2 -> 57
A4: Biweekly Payment | B4: 365.72 | D4: Years to Payoff | E4: =E3/B5 -> 2.1923077
A5: Payments Per Year | B5: 26 | D5: Total Interest Paid | E5: =Amortization!M3 -> 1973.6559
A6: Start Date (for reference) | B6: Apr 2026 | D6: Total Payments Made | E6: =Amortization!M4 -> 29363.656
A7: Rate Per Period | B7: =B3/B5 -> 0.0023076923 | D7: Total Lump Sums Applied | E7: =B10+B11+B13 -> 9500
A9: LUMP SUM PAYMENTS | D9: BASELINE COMPARISON
A10: Lump Sum #1 (apply at start) | B10: 9500 | D10: Baseline Periods (no changes) | E10: =Baseline!J2 -> 115
A11: Lump Sum #2 Amount | B11: 0 | D11: Baseline Total Interest | E11: =Baseline!J3 -> 5151.5318
A12: Lump Sum #2 - Apply at Period # | B12: 0 | D12: Periods Saved | E12: =E10-E3 -> 58
A13: Lump Sum #3 Amount | B13: 0 | D13: Interest Saved | E13: =E11-E5 -> 3177.8759
A14: Lump Sum #3 - Apply at Period # | B14: 0 | D14: Years Saved | E14: =E12/B5 -> 2.2307692
A16: PAYMENT INCREASES
A17: Extra Payment #1 Amount (biweekly) | B17: 197.44
A18: Extra Payment #1 - Starts at Period # | B18: 13
A19: Extra Payment #2 Amount (biweekly) | B19: 0
A20: Extra Payment #2 - Starts at Period # | B20: 0
A21: Extra Payment #3 Amount (biweekly) | B21: 0
A22: Extra Payment #3 - Starts at Period # | B22: 0
A24: HOW TO USE
A25: Change any BLUE value above to model different scenarios.
A26: Lump Sum #1 is applied immediately. #2 and #3 apply at the period you specify.
A27: Extra Payments add to your biweekly payment starting at the period you specify.
A28: Example: Wife's car paid off at period 13 → enter 197.44 as Extra Payment #1 starting at period 13.
A29: The Amortization tab shows the full period-by-period breakdown.
A30: The Baseline tab shows what happens with no changes for comparison.

Sheet Amortization
A1: Period | B1: Opening Balance | C1: Lump Sum Applied | D1: Payment | E1: Extra Payment | F1: Total Payment | G1: Interest | H1: Principal | I1: Closing Balance | J1: Cumulative Interest | L1: Summary
A2: 1 | B2: ='Loan Calculator'!B2-'Loan Calculator'!B10 -> 27390 | C2: =IF(B2<=0,0,IF(A2='Loan Calculator'!B12,MIN('Loan Calculator'!B11,B2),0)+IF(A2='Loan Calculator'!B14,MIN('Loan Calculator'!B13,B2),0)) -> 0 | D2: =IF(B2<=0,0,'Loan Calculator'!B4) -> 365.72 | E2: =IF(B2<=0,0,IF(A2>='Loan Calculator'!B18,'Loan Calculator'!B17,0)+IF(A2>='Loan Calculator'!B20,'Loan Calculator'!B19,0)+IF(A2>='Loan Calculator'!B22,'Loan Calculator'!B21,0)) -> 0 | F2: =IF(B2<=0,0,MIN(D2+E2,(B2-C2)*(1+'Loan Calculator'!B7))) -> 365.72 | G2: =IF(B2<=0,0,MAX(0,(B2-C2)*'Loan Calculator'!B7)) -> 63.207692 | H2: =IF(B2<=0,0,F2-G2) -> 302.51231 | I2: =IF(B2<=0,0,MAX(0,B2-C2-H2)) -> 27087.488 | J2: =G2 -> 63.207692 | L2: Total Periods: | M2: =COUNTIF(B2:B201,">"&0) -> 57
A3: 2 | B3: =MAX(0,I2) -> 27087.488 | C3: =IF(B3<=0,0,IF(A3='Loan Calculator'!B12,MIN('Loan Calculator'!B11,B3),0)+IF(A3='Loan Calculator'!B14,MIN('Loan Calculator'!B13,B3),0)) -> 0 | D3: =IF(B3<=0,0,'Loan Calculator'!B4) -> 365.72 | E3: =IF(B3<=0,0,IF(A3>='Loan Calculator'!B18,'Loan Calculator'!B17,0)+IF(A3>='Loan Calculator'!B20,'Loan Calculator'!B19,0)+IF(A3>='Loan Calculator'!B22,'Loan Calculator'!B21,0)) -> 0 | F3: =IF(B3<=0,0,MIN(D3+E3,(B3-C3)*(1+'Loan Calculator'!B7))) -> 365.72 | G3: =IF(B3<=0,0,MAX(0,(B3-C3)*'Loan Calculator'!B7)) -> 62.509587 | H3: =IF(B3<=0,0,F3-G3) -> 303.21041 | I3: =IF(B3<=0,0,MAX(0,B3-C3-H3)) -> 26784.277 | J3: =J2+G3 -> 125.71728 | L3: Total Interest: | M3: =SUM(G2:G201) -> 1973.6559
A4: 3 | B4: =MAX(0,I3) -> 26784.277 | C4: =IF(B4<=0,0,IF(A4='Loan Calculator'!B12,MIN('Loan Calculator'!B11,B4),0)+IF(A4='Loan Calculator'!B14,MIN('Loan Calculator'!B13,B4),0)) -> 0 | D4: =IF(B4<=0,0,'Loan Calculator'!B4) -> 365.72 | E4: =IF(B4<=0,0,IF(A4>='Loan Calculator'!B18,'Loan Calculator'!B17,0)+IF(A4>='Loan Calculator'!B20,'Loan Calculator'!B19,0)+IF(A4>='Loan Calculator'!B22,'Loan Calculator'!B21,0)) -> 0 | F4: =IF(B4<=0,0,MIN(D4+E4,(B4-C4)*(1+'Loan Calculator'!B7))) -> 365.72 | G4: =IF(B4<=0,0,MAX(0,(B4-C4)*'Loan Calculator'!B7)) -> 61.809871 | H4: =IF(B4<=0,0,F4-G4) -> 303.91013 | I4: =IF(B4<=0,0,MAX(0,B4-C4-H4)) -> 26480.367 | J4: =J3+G4 -> 187.52715 | L4: Total Payments: | M4: =SUM(F2:F201)+SUM(C2:C201) -> 29363.656
A5: 4 | B5: =MAX(0,I4) -> 26480.367 | C5: =IF(B5<=0,0,IF(A5='Loan Calculator'!B12,MIN('Loan Calculator'!B11,B5),0)+IF(A5='Loan Calculator'!B14,MIN('Loan Calculator'!B13,B5),0)) -> 0 | D5: =IF(B5<=0,0,'Loan Calculator'!B4) -> 365.72 | E5: =IF(B5<=0,0,IF(A5>='Loan Calculator'!B18,'Loan Calculator'!B17,0)+IF(A5>='Loan Calculator'!B20,'Loan Calculator'!B19,0)+IF(A5>='Loan Calculator'!B22,'Loan Calculator'!B21,0)) -> 0 | F5: =IF(B5<=0,0,MIN(D5+E5,(B5-C5)*(1+'Loan Calculator'!B7))) -> 365.72 | G5: =IF(B5<=0,0,MAX(0,(B5-C5)*'Loan Calculator'!B7)) -> 61.10854 | H5: =IF(B5<=0,0,F5-G5) -> 304.61146 | I5: =IF(B5<=0,0,MAX(0,B5-C5-H5)) -> 26175.756 | J5: =J4+G5 -> 248.63569
A6: 5 | B6: =MAX(0,I5) -> 26175.756 | C6: =IF(B6<=0,0,IF(A6='Loan Calculator'!B12,MIN('Loan Calculator'!B11,B6),0)+IF(A6='Loan Calculator'!B14,MIN('Loan Calculator'!B13,B6),0)) -> 0 | D6: =IF(B6<=0,0,'Loan Calculator'!B4) -> 365.72 | E6: =IF(B6<=0,0,IF(A6>='Loan Calculator'!B18,'Loan Calculator'!B17,0)+IF(A6>='Loan Calculator'!B20,'Loan Calculator'!B19,0)+IF(A6>='Loan Calculator'!B22,'Loan Calculator'!B21,0)) -> 0 | F6: =IF(B6<=0,0,MIN(D6+E6,(B6-C6)*(1+'Loan Calculator'!B7))) -> 365.72 | G6: =IF(B6<=0,0,MAX(0,(B6-C6)*'Loan Calculator'!B7)) -> 60.40559 | H6: =IF(B6<=0,0,F6-G6) -> 305.31441 | I6: =IF(B6<=0,0,MAX(0,B6-C6-H6)) -> 25870.441 | J6: =J5+G6 -> 309.04128
A7: 6 | B7: =MAX(0,I6) -> 25870.441 | C7: =IF(B7<=0,0,IF(A7='Loan Calculator'!B12,MIN('Loan Calculator'!B11,B7),0)+IF(A7='Loan Calculator'!B14,MIN('Loan Calculator'!B13,B7),0)) -> 0 | D7: =IF(B7<=0,0,'Loan Calculator'!B4) -> 365.72 | E7: =IF(B7<=0,0,IF(A7>='Loan Calculator'!B18,'Loan Calculator'!B17,0)+IF(A7>='Loan Calculator'!B20,'Loan Calculator'!B19,0)+IF(A7>='Loan Calculator'!B22,'Loan Calculator'!B21,0)) -> 0 | F7: =IF(B7<=0,0,MIN(D7+E7,(B7-C7)*(1+'Loan Calculator'!B7))) -> 365.72 | G7: =IF(B7<=0,0,MAX(0,(B7-C7)*'Loan Calculator'!B7)) -> 59.701018 | H7: =IF(B7<=0,0,F7-G7) -> 306.01898 | I7: =IF(B7<=0,0,MAX(0,B7-C7-H7)) -> 25564.422 | J7: =J6+G7 -> 368.7423
A8: 7 | B8: =MAX(0,I7) -> 25564.422 | C8: =IF(B8<=0,0,IF(A8='Loan Calculator'!B12,MIN('Loan Calculator'!B11,B8),0)+IF(A8='Loan Calculator'!B14,MIN('Loan Calculator'!B13,B8),0)) -> 0 | D8: =IF(B8<=0,0,'Loan Calculator'!B4) -> 365.72 | E8: =IF(B8<=0,0,IF(A8>='Loan Calculator'!B18,'Loan Calculator'!B17,0)+IF(A8>='Loan Calculator'!B20,'Loan Calculator'!B19,0)+IF(A8>='Loan Calculator'!B22,'Loan Calculator'!B21,0)) -> 0 | F8: =IF(B8<=0,0,MIN(D8+E8,(B8-C8)*(1+'Loan Calculator'!B7))) -> 365.72 | G8: =IF(B8<=0,0,MAX(0,(B8-C8)*'Loan Calculator'!B7)) -> 58.994821 | H8: =IF(B8<=0,0,F8-G8) -> 306.72518 | I8: =IF(B8<=0,0,MAX(0,B8-C8-H8)) -> 25257.697 | J8: =J7+G8 -> 427.73712
A9: 8 | B9: =MAX(0,I8) -> 25257.697 | C9: =IF(B9<=0,0,IF(A9='Loan Calculator'!B12,MIN('Loan Calculator'!B11,B9),0)+IF(A9='Loan Calculator'!B14,MIN('Loan Calculator'!B13,B9),0)) -> 0 | D9: =IF(B9<=0,0,'Loan Calculator'!B4) -> 365.72 | E9: =IF(B9<=0,0,IF(A9>='Loan Calculator'!B18,'Loan Calculator'!B17,0)+IF(A9>='Loan Calculator'!B20,'Loan Calculator'!B19,0)+IF(A9>='Loan Calculator'!B22,'Loan Calculator'!B21,0)) -> 0 | F9: =IF(B9<=0,0,MIN(D9+E9,(B9-C9)*(1+'Loan Calculator'!B7))) -> 365.72 | G9: =IF(B9<=0,0,MAX(0,(B9-C9)*'Loan Calculator'!B7)) -> 58.286993 | H9: =IF(B9<=0,0,F9-G9) -> 307.43301 | I9: =IF(B9<=0,0,MAX(0,B9-C9-H9)) -> 24950.264 | J9: =J8+G9 -> 486.02411
A10: 9 | B10: =MAX(0,I9) -> 24950.264 | C10: =IF(B10<=0,0,IF(A10='Loan Calculator'!B12,MIN('Loan Calculator'!B11,B10),0)+IF(A10='Loan Calculator'!B14,MIN('Loan Calculator'!B13,B10),0)) -> 0 | D10: =IF(B10<=0,0,'Loan Calculator'!B4) -> 365.72 | E10: =IF(B10<=0,0,IF(A10>='Loan Calculator'!B18,'Loan Calculator'!B17,0)+IF(A10>='Loan Calculator'!B20,'Loan Calculator'!B19,0)+IF(A10>='Loan Calculator'!B22,'Loan Calculator'!B21,0)) -> 0 | F10: =IF(B10<=0,0,MIN(D10+E10,(B10-C10)*(1+'Loan Calculator'!B7))) -> 365.72 | G10: =IF(B10<=0,0,MAX(0,(B10-C10)*'Loan Calculator'!B7)) -> 57.577533 | H10: =IF(B10<=0,0,F10-G10) -> 308.14247 | I10: =IF(B10<=0,0,MAX(0,B10-C10-H10)) -> 24642.122 | J10: =J9+G10 -> 543.60164
A11: 10 | B11: =MAX(0,I10) -> 24642.122 | C11: =IF(B11<=0,0,IF(A11='Loan Calculator'!B12,MIN('Loan Calculator'!B11,B11),0)+IF(A11='Loan Calculator'!B14,MIN('Loan Calculator'!B13,B11),0)) -> 0 | D11: =IF(B11<=0,0,'Loan Calculator'!B4) -> 365.72 | E11: =IF(B11<=0,0,IF(A11>='Loan Calculator'!B18,'Loan Calculator'!B17,0)+IF(A11>='Loan Calculator'!B20,'Loan Calculator'!B19,0)+IF(A11>='Loan Calculator'!B22,'Loan Calculator'!B21,0)) -> 0 | F11: =IF(B11<=0,0,MIN(D11+E11,(B11-C11)*(1+'Loan Calculator'!B7))) -> 365.72 | G11: =IF(B11<=0,0,MAX(0,(B11-C11)*'Loan Calculator'!B7)) -> 56.866435 | H11: =IF(B11<=0,0,F11-G11) -> 308.85357 | I11: =IF(B11<=0,0,MAX(0,B11-C11-H11)) -> 24333.268 | J11: =J10+G11 -> 600.46808
A12: 11 | B12: =MAX(0,I11) -> 24333.268 | C12: =IF(B12<=0,0,IF(A12='Loan Calculator'!B12,MIN('Loan Calculator'!B11,B12),0)+IF(A12='Loan Calculator'!B14,MIN('Loan Calculator'!B13,B12),0)) -> 0 | D12: =IF(B12<=0,0,'Loan Calculator'!B4) -> 365.72 | E12: =IF(B12<=0,0,IF(A12>='Loan Calculator'!B18,'Loan Calculator'!B17,0)+IF(A12>='Loan Calculator'!B20,'Loan Calculator'!B19,0)+IF(A12>='Loan Calculator'!B22,'Loan Calculator'!B21,0)) -> 0 | F12: =IF(B12<=0,0,MIN(D12+E12,(B12-C12)*(1+'Loan Calculator'!B7))) -> 365.72 | G12: =IF(B12<=0,0,MAX(0,(B12-C12)*'Loan Calculator'!B7)) -> 56.153696 | H12: =IF(B12<=0,0,F12-G12) -> 309.5663 | I12: =IF(B12<=0,0,MAX(0,B12-C12-H12)) -> 24023.702 | J12: =J11+G12 -> 656.62177
A13: 12 | B13: =MAX(0,I12) -> 24023.702 | C13: =IF(B13<=0,0,IF(A13='Loan Calculator'!B12,MIN('Loan Calculator'!B11,B13),0)+IF(A13='Loan Calculator'!B14,MIN('Loan Calculator'!B13,B13),0)) -> 0 | D13: =IF(B13<=0,0,'Loan Calculator'!B4) -> 365.72 | E13: =IF(B13<=0,0,IF(A13>='Loan Calculator'!B18,'Loan Calculator'!B17,0)+IF(A13>='Loan Calculator'!B20,'Loan Calculator'!B19,0)+IF(A13>='Loan Calculator'!B22,'Loan Calculator'!B21,0)) -> 0 | F13: =IF(B13<=0,0,MIN(D13+E13,(B13-C13)*(1+'Loan Calculator'!B7))) -> 365.72 | G13: =IF(B13<=0,0,MAX(0,(B13-C13)*'Loan Calculator'!B7)) -> 55.439312 | H13: =IF(B13<=0,0,F13-G13) -> 310.28069 | I13: =IF(B13<=0,0,MAX(0,B13-C13-H13)) -> 23713.421 | J13: =J12+G13 -> 712.06109
A14: 13 | B14: =MAX(0,I13) -> 23713.421 | C14: =IF(B14<=0,0,IF(A14='Loan Calculator'!B12,MIN('Loan Calculator'!B11,B14),0)+IF(A14='Loan Calculator'!B14,MIN('Loan Calculator'!B13,B14),0)) -> 0 | D14: =IF(B14<=0,0,'Loan Calculator'!B4) -> 365.72 | E14: =IF(B14<=0,0,IF(A14>='Loan Calculator'!B18,'Loan Calculator'!B17,0)+IF(A14>='Loan Calculator'!B20,'Loan Calculator'!B19,0)+IF(A14>='Loan Calculator'!B22,'Loan Calculator'!B21,0)) -> 197.44 | F14: =IF(B14<=0,0,MIN(D14+E14,(B14-C14)*(1+'Loan Calculator'!B7))) -> 563.16 | G14: =IF(B14<=0,0,MAX(0,(B14-C14)*'Loan Calculator'!B7)) -> 54.723279 | H14: =IF(B14<=0,0,F14-G14) -> 508.43672 | I14: =IF(B14<=0,0,MAX(0,B14-C14-H14)) -> 23204.984 | J14: =J13+G14 -> 766.78437
A15: 14 | B15: =MAX(0,I14) -> 23204.984 | C15: =IF(B15<=0,0,IF(A15='Loan Calculator'!B12,MIN('Loan Calculator'!B11,B15),0)+IF(A15='Loan Calculator'!B14,MIN('Loan Calculator'!B13,B15),0)) -> 0 | D15: =IF(B15<=0,0,'Loan Calculator'!B4) -> 365.72 | E15: =IF(B15<=0,0,IF(A15>='Loan Calculator'!B18,'Loan Calculator'!B17,0)+IF(A15>='Loan Calculator'!B20,'Loan Calculator'!B19,0)+IF(A15>='Loan Calculator'!B22,'Loan Calculator'!B21,0)) -> 197.44 | F15: =IF(B15<=0,0,MIN(D15+E15,(B15-C15)*(1+'Loan Calculator'!B7))) -> 563.16 | G15: =IF(B15<=0,0,MAX(0,(B15-C15)*'Loan Calculator'!B7)) -> 53.549964 | H15: =IF(B15<=0,0,F15-G15) -> 509.61004 | I15: =IF(B15<=0,0,MAX(0,B15-C15-H15)) -> 22695.374 | J15: =J14+G15 -> 820.33433
A16: 15 | B16: =MAX(0,I15) -> 22695.374 | C16: =IF(B16<=0,0,IF(A16='Loan Calculator'!B12,MIN('Loan Calculator'!B11,B16),0)+IF(A16='Loan Calculator'!B14,MIN('Loan Calculator'!B13,B16),0)) -> 0 | D16: =IF(B16<=0,0,'Loan Calculator'!B4) -> 365.72 | E16: =IF(B16<=0,0,IF(A16>='Loan Calculator'!B18,'Loan Calculator'!B17,0)+IF(A16>='Loan Calculator'!B20,'Loan Calculator'!B19,0)+IF(A16>='Loan Calculator'!B22,'Loan Calculator'!B21,0)) -> 197.44 | F16: =IF(B16<=0,0,MIN(D16+E16,(B16-C16)*(1+'Loan Calculator'!B7))) -> 563.16 | G16: =IF(B16<=0,0,MAX(0,(B16-C16)*'Loan Calculator'!B7)) -> 52.373941 | H16: =IF(B16<=0,0,F16-G16) -> 510.78606 | I16: =IF(B16<=0,0,MAX(0,B16-C16-H16)) -> 22184.588 | J16: =J15+G16 -> 872.70827
A17: 16 | B17: =MAX(0,I16) -> 22184.588 | C17: =IF(B17<=0,0,IF(A17='Loan Calculator'!B12,MIN('Loan Calculator'!B11,B17),0)+IF(A17='Loan Calculator'!B14,MIN('Loan Calculator'!B13,B17),0)) -> 0 | D17: =IF(B17<=0,0,'Loan Calculator'!B4) -> 365.72 | E17: =IF(B17<=0,0,IF(A17>='Loan Calculator'!B18,'Loan Calculator'!B17,0)+IF(A17>='Loan Calculator'!B20,'Loan Calculator'!B19,0)+IF(A17>='Loan Calculator'!B22,'Loan Calculator'!B21,0)) -> 197.44 | F17: =IF(B17<=0,0,MIN(D17+E17,(B17-C17)*(1+'Loan Calculator'!B7))) -> 563.16 | G17: =IF(B17<=0,0,MAX(0,(B17-C17)*'Loan Calculator'!B7)) -> 51.195204 | H17: =IF(B17<=0,0,F17-G17) -> 511.9648 | I17: =IF(B17<=0,0,MAX(0,B17-C17-H17)) -> 21672.623 | J17: =J16+G17 -> 923.90347
A18: 17 | B18: =MAX(0,I17) -> 21672.623 | C18: =IF(B18<=0,0,IF(A18='Loan Calculator'!B12,MIN('Loan Calculator'!B11,B18),0)+IF(A18='Loan Calculator'!B14,MIN('Loan Calculator'!B13,B18),0)) -> 0 | D18: =IF(B18<=0,0,'Loan Calculator'!B4) -> 365.72 | E18: =IF(B18<=0,0,IF(A18>='Loan Calculator'!B18,'Loan Calculator'!B17,0)+IF(A18>='Loan Calculator'!B20,'Loan Calculator'!B19,0)+IF(A18>='Loan Calculator'!B22,'Loan Calculator'!B21,0)) -> 197.44 | F18: =IF(B18<=0,0,MIN(D18+E18,(B18-C18)*(1+'Loan Calculator'!B7))) -> 563.16 | G18: =IF(B18<=0,0,MAX(0,(B18-C18)*'Loan Calculator'!B7)) -> 50.013746 | H18: =IF(B18<=0,0,F18-G18) -> 513.14625 | I18: =IF(B18<=0,0,MAX(0,B18-C18-H18)) -> 21159.477 | J18: =J17+G18 -> 973.91722
A19: 18 | B19: =MAX(0,I18) -> 21159.477 | C19: =IF(B19<=0,0,IF(A19='Loan Calculator'!B12,MIN('Loan Calculator'!B11,B19),0)+IF(A19='Loan Calculator'!B14,MIN('Loan Calculator'!B13,B19),0)) -> 0 | D19: =IF(B19<=0,0,'Loan Calculator'!B4) -> 365.72 | E19: =IF(B19<=0,0,IF(A19>='Loan Calculator'!B18,'Loan Calculator'!B17,0)+IF(A19>='Loan Calculator'!B20,'Loan Calculator'!B19,0)+IF(A19>='Loan Calculator'!B22,'Loan Calculator'!B21,0)) -> 197.44 | F19: =IF(B19<=0,0,MIN(D19+E19,(B19-C19)*(1+'Loan Calculator'!B7))) -> 563.16 | G19: =IF(B19<=0,0,MAX(0,(B19-C19)*'Loan Calculator'!B7)) -> 48.829563 | H19: =IF(B19<=0,0,F19-G19) -> 514.33044 | I19: =IF(B19<=0,0,MAX(0,B19-C19-H19)) -> 20645.147 | J19: =J18+G19 -> 1022.7468
A20: 19 | B20: =MAX(0,I19) -> 20645.147 | C20: =IF(B20<=0,0,IF(A20='Loan Calculator'!B12,MIN('Loan Calculator'!B11,B20),0)+IF(A20='Loan Calculator'!B14,MIN('Loan Calculator'!B13,B20),0)) -> 0 | D20: =IF(B20<=0,0,'Loan Calculator'!B4) -> 365.72 | E20: =IF(B20<=0,0,IF(A20>='Loan Calculator'!B18,'Loan Calculator'!B17,0)+IF(A20>='Loan Calculator'!B20,'Loan Calculator'!B19,0)+IF(A20>='Loan Calculator'!B22,'Loan Calculator'!B21,0)) -> 197.44 | F20: =IF(B20<=0,0,MIN(D20+E20,(B20-C20)*(1+'Loan Calculator'!B7))) -> 563.16 | G20: =IF(B20<=0,0,MAX(0,(B20-C20)*'Loan Calculator'!B7)) -> 47.642646 | H20: =IF(B20<=0,0,F20-G20) -> 515.51735 | I20: =IF(B20<=0,0,MAX(0,B20-C20-H20)) -> 20129.629 | J20: =J19+G20 -> 1070.3894
A21: 20 | B21: =MAX(0,I20) -> 20129.629 | C21: =IF(B21<=0,0,IF(A21='Loan Calculator'!B12,MIN('Loan Calculator'!B11,B21),0)+IF(A21='Loan Calculator'!B14,MIN('Loan Calculator'!B13,B21),0)) -> 0 | D21: =IF(B21<=0,0,'Loan Calculator'!B4) -> 365.72 | E21: =IF(B21<=0,0,IF(A21>='Loan Calculator'!B18,'Loan Calculator'!B17,0)+IF(A21>='Loan Calculator'!B20,'Loan Calculator'!B19,0)+IF(A21>='Loan Calculator'!B22,'Loan Calculator'!B21,0)) -> 197.44 | F21: =IF(B21<=0,0,MIN(D21+E21,(B21-C21)*(1+'Loan Calculator'!B7))) -> 563.16 | G21: =IF(B21<=0,0,MAX(0,(B21-C21)*'Loan Calculator'!B7)) -> 46.452991 | H21: =IF(B21<=0,0,F21-G21) -> 516.70701 | I21: =IF(B21<=0,0,MAX(0,B21-C21-H21)) -> 19612.922 | J21: =J20+G21 -> 1116.8424
A22: 21 | B22: =MAX(0,I21) -> 19612.922 | C22: =IF(B22<=0,0,IF(A22='Loan Calculator'!B12,MIN('Loan Calculator'!B11,B22),0)+IF(A22='Loan Calculator'!B14,MIN('Loan Calculator'!B13,B22),0)) -> 0 | D22: =IF(B22<=0,0,'Loan Calculator'!B4) -> 365.72 | E22: =IF(B22<=0,0,IF(A22>='Loan Calculator'!B18,'Loan Calculator'!B17,0)+IF(A22>='Loan Calculator'!B20,'Loan Calculator'!B19,0)+IF(A22>='Loan Calculator'!B22,'Loan Calculator'!B21,0)) -> 197.44 | F22: =IF(B22<=0,0,MIN(D22+E22,(B22-C22)*(1+'Loan Calculator'!B7))) -> 563.16 | G22: =IF(B22<=0,0,MAX(0,(B22-C22)*'Loan Calculator'!B7)) -> 45.26059 | H22: =IF(B22<=0,0,F22-G22) -> 517.89941 | I22: =IF(B22<=0,0,MAX(0,B22-C22-H22)) -> 19095.023 | J22: =J21+G22 -> 1162.103
A23: 22 | B23: =MAX(0,I22) -> 19095.023 | C23: =IF(B23<=0,0,IF(A23='Loan Calculator'!B12,MIN('Loan Calculator'!B11,B23),0)+IF(A23='Loan Calculator'!B14,MIN('Loan Calculator'!B13,B23),0)) -> 0 | D23: =IF(B23<=0,0,'Loan Calculator'!B4) -> 365.72 | E23: =IF(B23<=0,0,IF(A23>='Loan Calculator'!B18,'Loan Calculator'!B17,0)+IF(A23>='Loan Calculator'!B20,'Loan Calculator'!B19,0)+IF(A23>='Loan Calculator'!B22,'Loan Calculator'!B21,0)) -> 197.44 | F23: =IF(B23<=0,0,MIN(D23+E23,(B23-C23)*(1+'Loan Calculator'!B7))) -> 563.16 | G23: =IF(B23<=0,0,MAX(0,(B23-C23)*'Loan Calculator'!B7)) -> 44.065438 | H23: =IF(B23<=0,0,F23-G23) -> 519.09456 | I23: =IF(B23<=0,0,MAX(0,B23-C23-H23)) -> 18575.928 | J23: =J22+G23 -> 1206.1684
A24: 23 | B24: =MAX(0,I23) -> 18575.928 | C24: =IF(B24<=0,0,IF(A24='Loan Calculator'!B12,MIN('Loan Calculator'!B11,B24),0)+IF(A24='Loan Calculator'!B14,MIN('Loan Calculator'!B13,B24),0)) -> 0 | D24: =IF(B24<=0,0,'Loan Calculator'!B4) -> 365.72 | E24: =IF(B24<=0,0,IF(A24>='Loan Calculator'!B18,'Loan Calculator'!B17,0)+IF(A24>='Loan Calculator'!B20,'Loan Calculator'!B19,0)+IF(A24>='Loan Calculator'!B22,'Loan Calculator'!B21,0)) -> 197.44 | F24: =IF(B24<=0,0,MIN(D24+E24,(B24-C24)*(1+'Loan Calculator'!B7))) -> 563.16 | G24: =IF(B24<=0,0,MAX(0,(B24-C24)*'Loan Calculator'!B7)) -> 42.867527 | H24: =IF(B24<=0,0,F24-G24) -> 520.29247 | I24: =IF(B24<=0,0,MAX(0,B24-C24-H24)) -> 18055.636 | J24: =J23+G24 -> 1249.036
A25: 24 | B25: =MAX(0,I24) -> 18055.636 | C25: =IF(B25<=0,0,IF(A25='Loan Calculator'!B12,MIN('Loan Calculator'!B11,B25),0)+IF(A25='Loan Calculator'!B14,MIN('Loan Calculator'!B13,B25),0)) -> 0 | D25: =IF(B25<=0,0,'Loan Calculator'!B4) -> 365.72 | E25: =IF(B25<=0,0,IF(A25>='Loan Calculator'!B18,'Loan Calculator'!B17,0)+IF(A25>='Loan Calculator'!B20,'Loan Calculator'!B19,0)+IF(A25>='Loan Calculator'!B22,'Loan Calculator'!B21,0)) -> 197.44 | F25: =IF(B25<=0,0,MIN(D25+E25,(B25-C25)*(1+'Loan Calculator'!B7))) -> 563.16 | G25: =IF(B25<=0,0,MAX(0,(B25-C25)*'Loan Calculator'!B7)) -> 41.666852 | H25: =IF(B25<=0,0,F25-G25) -> 521.49315 | I25: =IF(B25<=0,0,MAX(0,B25-C25-H25)) -> 17534.143 | J25: =J24+G25 -> 1290.7028
A26: 25 | B26: =MAX(0,I25) -> 17534.143 | C26: =IF(B26<=0,0,IF(A26='Loan Calculator'!B12,MIN('Loan Calculator'!B11,B26),0)+IF(A26='Loan Calculator'!B14,MIN('Loan Calculator'!B13,B26),0)) -> 0 | D26: =IF(B26<=0,0,'Loan Calculator'!B4) -> 365.72 | E26: =IF(B26<=0,0,IF(A26>='Loan Calculator'!B18,'Loan Calculator'!B17,0)+IF(A26>='Loan Calculator'!B20,'Loan Calculator'!B19,0)+IF(A26>='Loan Calculator'!B22,'Loan Calculator'!B21,0)) -> 197.44 | F26: =IF(B26<=0,0,MIN(D26+E26,(B26-C26)*(1+'Loan Calculator'!B7))) -> 563.16 | G26: =IF(B26<=0,0,MAX(0,(B26-C26)*'Loan Calculator'!B7)) -> 40.463407 | H26: =IF(B26<=0,0,F26-G26) -> 522.69659 | I26: =IF(B26<=0,0,MAX(0,B26-C26-H26)) -> 17011.446 | J26: =J25+G26 -> 1331.1662
A27: 26 | B27: =MAX(0,I26) -> 17011.446 | C27: =IF(B27<=0,0,IF(A27='Loan Calculator'!B12,MIN('Loan Calculator'!B11,B27),0)+IF(A27='Loan Calculator'!B14,MIN('Loan Calculator'!B13,B27),0)) -> 0 | D27: =IF(B27<=0,0,'Loan Calculator'!B4) -> 365.72 | E27: =IF(B27<=0,0,IF(A27>='Loan Calculator'!B18,'Loan Calculator'!B17,0)+IF(A27>='Loan Calculator'!B20,'Loan Calculator'!B19,0)+IF(A27>='Loan Calculator'!B22,'Loan Calculator'!B21,0)) -> 197.44 | F27: =IF(B27<=0,0,MIN(D27+E27,(B27-C27)*(1+'Loan Calculator'!B7))) -> 563.16 | G27: =IF(B27<=0,0,MAX(0,(B27-C27)*'Loan Calculator'!B7)) -> 39.257184 | H27: =IF(B27<=0,0,F27-G27) -> 523.90282 | I27: =IF(B27<=0,0,MAX(0,B27-C27-H27)) -> 16487.543 | J27: =J26+G27 -> 1370.4234
A28: 27 | B28: =MAX(0,I27) -> 16487.543 | C28: =IF(B28<=0,0,IF(A28='Loan Calculator'!B12,MIN('Loan Calculator'!B11,B28),0)+IF(A28='Loan Calculator'!B14,MIN('Loan Calculator'!B13,B28),0)) -> 0 | D28: =IF(B28<=0,0,'Loan Calculator'!B4) -> 365.72 | E28: =IF(B28<=0,0,IF(A28>='Loan Calculator'!B18,'Loan Calculator'!B17,0)+IF(A28>='Loan Calculator'!B20,'Loan Calculator'!B19,0)+IF(A28>='Loan Calculator'!B22,'Loan Calculator'!B21,0)) -> 197.44 | F28: =IF(B28<=0,0,MIN(D28+E28,(B28-C28)*(1+'Loan Calculator'!B7))) -> 563.16 | G28: =IF(B28<=0,0,MAX(0,(B28-C28)*'Loan Calculator'!B7)) -> 38.048177 | H28: =IF(B28<=0,0,F28-G28) -> 525.11182 | I28: =IF(B28<=0,0,MAX(0,B28-C28-H28)) -> 15962.432 | J28: =J27+G28 -> 1408.4716
A29: 28 | B29: =MAX(0,I28) -> 15962.432 | C29: =IF(B29<=0,0,IF(A29='Loan Calculator'!B12,MIN('Loan Calculator'!B11,B29),0)+IF(A29='Loan Calculator'!B14,MIN('Loan Calculator'!B13,B29),0)) -> 0 | D29: =IF(B29<=0,0,'Loan Calculator'!B4) -> 365.72 | E29: =IF(B29<=0,0,IF(A29>='Loan Calculator'!B18,'Loan Calculator'!B17,0)+IF(A29>='Loan Calculator'!B20,'Loan Calculator'!B19,0)+IF(A29>='Loan Calculator'!B22,'Loan Calculator'!B21,0)) -> 197.44 | F29: =IF(B29<=0,0,MIN(D29+E29,(B29-C29)*(1+'Loan Calculator'!B7))) -> 563.16 | G29: =IF(B29<=0,0,MAX(0,(B29-C29)*'Loan Calculator'!B7)) -> 36.836381 | H29: =IF(B29<=0,0,F29-G29) -> 526.32362 | I29: =IF(B29<=0,0,MAX(0,B29-C29-H29)) -> 15436.108 | J29: =J28+G29 -> 1445.308
A30: 29 | B30: =MAX(0,I29) -> 15436.108 | C30: =IF(B30<=0,0,IF(A30='Loan Calculator'!B12,MIN('Loan Calculator'!B11,B30),0)+IF(A30='Loan Calculator'!B14,MIN('Loan Calculator'!B13,B30),0)) -> 0 | D30: =IF(B30<=0,0,'Loan Calculator'!B4) -> 365.72 | E30: =IF(B30<=0,0,IF(A30>='Loan Calculator'!B18,'Loan Calculator'!B17,0)+IF(A30>='Loan Calculator'!B20,'Loan Calculator'!B19,0)+IF(A30>='Loan Calculator'!B22,'Loan Calculator'!B21,0)) -> 197.44 | F30: =IF(B30<=0,0,MIN(D30+E30,(B30-C30)*(1+'Loan Calculator'!B7))) -> 563.16 | G30: =IF(B30<=0,0,MAX(0,(B30-C30)*'Loan Calculator'!B7)) -> 35.621788 | H30: =IF(B30<=0,0,F30-G30) -> 527.53821 | I30: =IF(B30<=0,0,MAX(0,B30-C30-H30)) -> 14908.57 | J30: =J29+G30 -> 1480.9298
A31: 30 | B31: =MAX(0,I30) -> 14908.57 | C31: =IF(B31<=0,0,IF(A31='Loan Calculator'!B12,MIN('Loan Calculator'!B11,B31),0)+IF(A31='Loan Calculator'!B14,MIN('Loan Calculator'!B13,B31),0)) -> 0 | D31: =IF(B31<=0,0,'Loan Calculator'!B4) -> 365.72 | E31: =IF(B31<=0,0,IF(A31>='Loan Calculator'!B18,'Loan Calculator'!B17,0)+IF(A31>='Loan Calculator'!B20,'Loan Calculator'!B19,0)+IF(A31>='Loan Calculator'!B22,'Loan Calculator'!B21,0)) -> 197.44 | F31: =IF(B31<=0,0,MIN(D31+E31,(B31-C31)*(1+'Loan Calculator'!B7))) -> 563.16 | G31: =IF(B31<=0,0,MAX(0,(B31-C31)*'Loan Calculator'!B7)) -> 34.404392 | H31: =IF(B31<=0,0,F31-G31) -> 528.75561 | I31: =IF(B31<=0,0,MAX(0,B31-C31-H31)) -> 14379.814 | J31: =J30+G31 -> 1515.3342
A32: 31 | B32: =MAX(0,I31) -> 14379.814 | C32: =IF(B32<=0,0,IF(A32='Loan Calculator'!B12,MIN('Loan Calculator'!B11,B32),0)+IF(A32='Loan Calculator'!B14,MIN('Loan Calculator'!B13,B32),0)) -> 0 | D32: =IF(B32<=0,0,'Loan Calculator'!B4) -> 365.72 | E32: =IF(B32<=0,0,IF(A32>='Loan Calculator'!B18,'Loan Calculator'!B17,0)+IF(A32>='Loan Calculator'!B20,'Loan Calculator'!B19,0)+IF(A32>='Loan Calculator'!B22,'Loan Calculator'!B21,0)) -> 197.44 | F32: =IF(B32<=0,0,MIN(D32+E32,(B32-C32)*(1+'Loan Calculator'!B7))) -> 563.16 | G32: =IF(B32<=0,0,MAX(0,(B32-C32)*'Loan Calculator'!B7)) -> 33.184187 | H32: =IF(B32<=0,0,F32-G32) -> 529.97581 | I32: =IF(B32<=0,0,MAX(0,B32-C32-H32)) -> 13849.838 | J32: =J31+G32 -> 1548.5183
A33: 32 | B33: =MAX(0,I32) -> 13849.838 | C33: =IF(B33<=0,0,IF(A33='Loan Calculator'!B12,MIN('Loan Calculator'!B11,B33),0)+IF(A33='Loan Calculator'!B14,MIN('Loan Calculator'!B13,B33),0)) -> 0 | D33: =IF(B33<=0,0,'Loan Calculator'!B4) -> 365.72 | E33: =IF(B33<=0,0,IF(A33>='Loan Calculator'!B18,'Loan Calculator'!B17,0)+IF(A33>='Loan Calculator'!B20,'Loan Calculator'!B19,0)+IF(A33>='Loan Calculator'!B22,'Loan Calculator'!B21,0)) -> 197.44 | F33: =IF(B33<=0,0,MIN(D33+E33,(B33-C33)*(1+'Loan Calculator'!B7))) -> 563.16 | G33: =IF(B33<=0,0,MAX(0,(B33-C33)*'Loan Calculator'!B7)) -> 31.961165 | H33: =IF(B33<=0,0,F33-G33) -> 531.19883 | I33: =IF(B33<=0,0,MAX(0,B33-C33-H33)) -> 13318.64 | J33: =J32+G33 -> 1580.4795
A34: 33 | B34: =MAX(0,I33) -> 13318.64 | C34: =IF(B34<=0,0,IF(A34='Loan Calculator'!B12,MIN('Loan Calculator'!B11,B34),0)+IF(A34='Loan Calculator'!B14,MIN('Loan Calculator'!B13,B34),0)) -> 0 | D34: =IF(B34<=0,0,'Loan Calculator'!B4) -> 365.72 | E34: =IF(B34<=0,0,IF(A34>='Loan Calculator'!B18,'Loan Calculator'!B17,0)+IF(A34>='Loan Calculator'!B20,'Loan Calculator'!B19,0)+IF(A34>='Loan Calculator'!B22,'Loan Calculator'!B21,0)) -> 197.44 | F34: =IF(B34<=0,0,MIN(D34+E34,(B34-C34)*(1+'Loan Calculator'!B7))) -> 563.16 | G34: =IF(B34<=0,0,MAX(0,(B34-C34)*'Loan Calculator'!B7)) -> 30.735322 | H34: =IF(B34<=0,0,F34-G34) -> 532.42468 | I34: =IF(B34<=0,0,MAX(0,B34-C34-H34)) -> 12786.215 | J34: =J33+G34 -> 1611.2148
A35: 34 | B35: =MAX(0,I34) -> 12786.215 | C35: =IF(B35<=0,0,IF(A35='Loan Calculator'!B12,MIN('Loan Calculator'!B11,B35),0)+IF(A35='Loan Calculator'!B14,MIN('Loan Calculator'!B13,B35),0)) -> 0 | D35: =IF(B35<=0,0,'Loan Calculator'!B4) -> 365.72 | E35: =IF(B35<=0,0,IF(A35>='Loan Calculator'!B18,'Loan Calculator'!B17,0)+IF(A35>='Loan Calculator'!B20,'Loan Calculator'!B19,0)+IF(A35>='Loan Calculator'!B22,'Loan Calculator'!B21,0)) -> 197.44 | F35: =IF(B35<=0,0,MIN(D35+E35,(B35-C35)*(1+'Loan Calculator'!B7))) -> 563.16 | G35: =IF(B35<=0,0,MAX(0,(B35-C35)*'Loan Calculator'!B7)) -> 29.50665 | H35: =IF(B35<=0,0,F35-G35) -> 533.65335 | I35: =IF(B35<=0,0,MAX(0,B35-C35-H35)) -> 12252.561 | J35: =J34+G35 -> 1640.7215
A36: 35 | B36: =MAX(0,I35) -> 12252.561 | C36: =IF(B36<=0,0,IF(A36='Loan Calculator'!B12,MIN('Loan Calculator'!B11,B36),0)+IF(A36='Loan Calculator'!B14,MIN('Loan Calculator'!B13,B36),0)) -> 0 | D36: =IF(B36<=0,0,'Loan Calculator'!B4) -> 365.72 | E36: =IF(B36<=0,0,IF(A36>='Loan Calculator'!B18,'Loan Calculator'!B17,0)+IF(A36>='Loan Calculator'!B20,'Loan Calculator'!B19,0)+IF(A36>='Loan Calculator'!B22,'Loan Calculator'!B21,0)) -> 197.44 | F36: =IF(B36<=0,0,MIN(D36+E36,(B36-C36)*(1+'Loan Calculator'!B7))) -> 563.16 | G36: =IF(B36<=0,0,MAX(0,(B36-C36)*'Loan Calculator'!B7)) -> 28.275142 | H36: =IF(B36<=0,0,F36-G36) -> 534.88486 | I36: =IF(B36<=0,0,MAX(0,B36-C36-H36)) -> 11717.677 | J36: =J35+G36 -> 1668.9966
A37: 36 | B37: =MAX(0,I36) -> 11717.677 | C37: =IF(B37<=0,0,IF(A37='Loan Calculator'!B12,MIN('Loan Calculator'!B11,B37),0)+IF(A37='Loan Calculator'!B14,MIN('Loan Calculator'!B13,B37),0)) -> 0 | D37: =IF(B37<=0,0,'Loan Calculator'!B4) -> 365.72 | E37: =IF(B37<=0,0,IF(A37>='Loan Calculator'!B18,'Loan Calculator'!B17,0)+IF(A37>='Loan Calculator'!B20,'Loan Calculator'!B19,0)+IF(A37>='Loan Calculator'!B22,'Loan Calculator'!B21,0)) -> 197.44 | F37: =IF(B37<=0,0,MIN(D37+E37,(B37-C37)*(1+'Loan Calculator'!B7))) -> 563.16 | G37: =IF(B37<=0,0,MAX(0,(B37-C37)*'Loan Calculator'!B7)) -> 27.040792 | H37: =IF(B37<=0,0,F37-G37) -> 536.11921 | I37: =IF(B37<=0,0,MAX(0,B37-C37-H37)) -> 11181.557 | J37: =J36+G37 -> 1696.0374
A38: 37 | B38: =MAX(0,I37) -> 11181.557 | C38: =IF(B38<=0,0,IF(A38='Loan Calculator'!B12,MIN('Loan Calculator'!B11,B38),0)+IF(A38='Loan Calculator'!B14,MIN('Loan Calculator'!B13,B38),0)) -> 0 | D38: =IF(B38<=0,0,'Loan Calculator'!B4) -> 365.72 | E38: =IF(B38<=0,0,IF(A38>='Loan Calculator'!B18,'Loan Calculator'!B17,0)+IF(A38>='Loan Calculator'!B20,'Loan Calculator'!B19,0)+IF(A38>='Loan Calculator'!B22,'Loan Calculator'!B21,0)) -> 197.44 | F38: =IF(B38<=0,0,MIN(D38+E38,(B38-C38)*(1+'Loan Calculator'!B7))) -> 563.16 | G38: =IF(B38<=0,0,MAX(0,(B38-C38)*'Loan Calculator'!B7)) -> 25.803594 | H38: =IF(B38<=0,0,F38-G38) -> 537.35641 | I38: =IF(B38<=0,0,MAX(0,B38-C38-H38)) -> 10644.201 | J38: =J37+G38 -> 1721.841
A39: 38 | B39: =MAX(0,I38) -> 10644.201 | C39: =IF(B39<=0,0,IF(A39='Loan Calculator'!B12,MIN('Loan Calculator'!B11,B39),0)+IF(A39='Loan Calculator'!B14,MIN('Loan Calculator'!B13,B39),0)) -> 0 | D39: =IF(B39<=0,0,'Loan Calculator'!B4) -> 365.72 | E39: =IF(B39<=0,0,IF(A39>='Loan Calculator'!B18,'Loan Calculator'!B17,0)+IF(A39>='Loan Calculator'!B20,'Loan Calculator'!B19,0)+IF(A39>='Loan Calculator'!B22,'Loan Calculator'!B21,0)) -> 197.44 | F39: =IF(B39<=0,0,MIN(D39+E39,(B39-C39)*(1+'Loan Calculator'!B7))) -> 563.16 | G39: =IF(B39<=0,0,MAX(0,(B39-C39)*'Loan Calculator'!B7)) -> 24.563541 | H39: =IF(B39<=0,0,F39-G39) -> 538.59646 | I39: =IF(B39<=0,0,MAX(0,B39-C39-H39)) -> 10105.605 | J39: =J38+G39 -> 1746.4045
A40: 39 | B40: =MAX(0,I39) -> 10105.605 | C40: =IF(B40<=0,0,IF(A40='Loan Calculator'!B12,MIN('Loan Calculator'!B11,B40),0)+IF(A40='Loan Calculator'!B14,MIN('Loan Calculator'!B13,B40),0)) -> 0 | D40: =IF(B40<=0,0,'Loan Calculator'!B4) -> 365.72 | E40: =IF(B40<=0,0,IF(A40>='Loan Calculator'!B18,'Loan Calculator'!B17,0)+IF(A40>='Loan Calculator'!B20,'Loan Calculator'!B19,0)+IF(A40>='Loan Calculator'!B22,'Loan Calculator'!B21,0)) -> 197.44 | F40: =IF(B40<=0,0,MIN(D40+E40,(B40-C40)*(1+'Loan Calculator'!B7))) -> 563.16 | G40: =IF(B40<=0,0,MAX(0,(B40-C40)*'Loan Calculator'!B7)) -> 23.320626 | H40: =IF(B40<=0,0,F40-G40) -> 539.83937 | I40: =IF(B40<=0,0,MAX(0,B40-C40-H40)) -> 9565.7652 | J40: =J39+G40 -> 1769.7252
A41: 40 | B41: =MAX(0,I40) -> 9565.7652 | C41: =IF(B41<=0,0,IF(A41='Loan Calculator'!B12,MIN('Loan Calculator'!B11,B41),0)+IF(A41='Loan Calculator'!B14,MIN('Loan Calculator'!B13,B41),0)) -> 0 | D41: =IF(B41<=0,0,'Loan Calculator'!B4) -> 365.72 | E41: =IF(B41<=0,0,IF(A41>='Loan Calculator'!B18,'Loan Calculator'!B17,0)+IF(A41>='Loan Calculator'!B20,'Loan Calculator'!B19,0)+IF(A41>='Loan Calculator'!B22,'Loan Calculator'!B21,0)) -> 197.44 | F41: =IF(B41<=0,0,MIN(D41+E41,(B41-C41)*(1+'Loan Calculator'!B7))) -> 563.16 | G41: =IF(B41<=0,0,MAX(0,(B41-C41)*'Loan Calculator'!B7)) -> 22.074843 | H41: =IF(B41<=0,0,F41-G41) -> 541.08516 | I41: =IF(B41<=0,0,MAX(0,B41-C41-H41)) -> 9024.68 | J41: =J40+G41 -> 1791.8
A42: 41 | B42: =MAX(0,I41) -> 9024.68 | C42: =IF(B42<=0,0,IF(A42='Loan Calculator'!B12,MIN('Loan Calculator'!B11,B42),0)+IF(A42='Loan Calculator'!B14,MIN('Loan Calculator'!B13,B42),0)) -> 0 | D42: =IF(B42<=0,0,'Loan Calculator'!B4) -> 365.72 | E42: =IF(B42<=0,0,IF(A42>='Loan Calculator'!B18,'Loan Calculator'!B17,0)+IF(A42>='Loan Calculator'!B20,'Loan Calculator'!B19,0)+IF(A42>='Loan Calculator'!B22,'Loan Calculator'!B21,0)) -> 197.44 | F42: =IF(B42<=0,0,MIN(D42+E42,(B42-C42)*(1+'Loan Calculator'!B7))) -> 563.16 | G42: =IF(B42<=0,0,MAX(0,(B42-C42)*'Loan Calculator'!B7)) -> 20.826185 | H42: =IF(B42<=0,0,F42-G42) -> 542.33382 | I42: =IF(B42<=0,0,MAX(0,B42-C42-H42)) -> 8482.3462 | J42: =J41+G42 -> 1812.6262
A43: 42 | B43: =MAX(0,I42) -> 8482.3462 | C43: =IF(B43<=0,0,IF(A43='Loan Calculator'!B12,MIN('Loan Calculator'!B11,B43),0)+IF(A43='Loan Calculator'!B14,MIN('Loan Calculator'!B13,B43),0)) -> 0 | D43: =IF(B43<=0,0,'Loan Calculator'!B4) -> 365.72 | E43: =IF(B43<=0,0,IF(A43>='Loan Calculator'!B18,'Loan Calculator'!B17,0)+IF(A43>='Loan Calculator'!B20,'Loan Calculator'!B19,0)+IF(A43>='Loan Calculator'!B22,'Loan Calculator'!B21,0)) -> 197.44 | F43: =IF(B43<=0,0,MIN(D43+E43,(B43-C43)*(1+'Loan Calculator'!B7))) -> 563.16 | G43: =IF(B43<=0,0,MAX(0,(B43-C43)*'Loan Calculator'!B7)) -> 19.574645 | H43: =IF(B43<=0,0,F43-G43) -> 543.58535 | I43: =IF(B43<=0,0,MAX(0,B43-C43-H43)) -> 7938.7608 | J43: =J42+G43 -> 1832.2008
A44: 43 | B44: =MAX(0,I43) -> 7938.7608 | C44: =IF(B44<=0,0,IF(A44='Loan Calculator'!B12,MIN('Loan Calculator'!B11,B44),0)+IF(A44='Loan Calculator'!B14,MIN('Loan Calculator'!B13,B44),0)) -> 0 | D44: =IF(B44<=0,0,'Loan Calculator'!B4) -> 365.72 | E44: =IF(B44<=0,0,IF(A44>='Loan Calculator'!B18,'Loan Calculator'!B17,0)+IF(A44>='Loan Calculator'!B20,'Loan Calculator'!B19,0)+IF(A44>='Loan Calculator'!B22,'Loan Calculator'!B21,0)) -> 197.44 | F44: =IF(B44<=0,0,MIN(D44+E44,(B44-C44)*(1+'Loan Calculator'!B7))) -> 563.16 | G44: =IF(B44<=0,0,MAX(0,(B44-C44)*'Loan Calculator'!B7)) -> 18.320217 | H44: =IF(B44<=0,0,F44-G44) -> 544.83978 | I44: =IF(B44<=0,0,MAX(0,B44-C44-H44)) -> 7393.9211 | J44: =J43+G44 -> 1850.5211
A45: 44 | B45: =MAX(0,I44) -> 7393.9211 | C45: =IF(B45<=0,0,IF(A45='Loan Calculator'!B12,MIN('Loan Calculator'!B11,B45),0)+IF(A45='Loan Calculator'!B14,MIN('Loan Calculator'!B13,B45),0)) -> 0 | D45: =IF(B45<=0,0,'Loan Calculator'!B4) -> 365.72 | E45: =IF(B45<=0,0,IF(A45>='Loan Calculator'!B18,'Loan Calculator'!B17,0)+IF(A45>='Loan Calculator'!B20,'Loan Calculator'!B19,0)+IF(A45>='Loan Calculator'!B22,'Loan Calculator'!B21,0)) -> 197.44 | F45: =IF(B45<=0,0,MIN(D45+E45,(B45-C45)*(1+'Loan Calculator'!B7))) -> 563.16 | G45: =IF(B45<=0,0,MAX(0,(B45-C45)*'Loan Calculator'!B7)) -> 17.062895 | H45: =IF(B45<=0,0,F45-G45) -> 546.09711 | I45: =IF(B45<=0,0,MAX(0,B45-C45-H45)) -> 6847.824 | J45: =J44+G45 -> 1867.584
A46: 45 | B46: =MAX(0,I45) -> 6847.824 | C46: =IF(B46<=0,0,IF(A46='Loan Calculator'!B12,MIN('Loan Calculator'!B11,B46),0)+IF(A46='Loan Calculator'!B14,MIN('Loan Calculator'!B13,B46),0)) -> 0 | D46: =IF(B46<=0,0,'Loan Calculator'!B4) -> 365.72 | E46: =IF(B46<=0,0,IF(A46>='Loan Calculator'!B18,'Loan Calculator'!B17,0)+IF(A46>='Loan Calculator'!B20,'Loan Calculator'!B19,0)+IF(A46>='Loan Calculator'!B22,'Loan Calculator'!B21,0)) -> 197.44 | F46: =IF(B46<=0,0,MIN(D46+E46,(B46-C46)*(1+'Loan Calculator'!B7))) -> 563.16 | G46: =IF(B46<=0,0,MAX(0,(B46-C46)*'Loan Calculator'!B7)) -> 15.802671 | H46: =IF(B46<=0,0,F46-G46) -> 547.35733 | I46: =IF(B46<=0,0,MAX(0,B46-C46-H46)) -> 6300.4666 | J46: =J45+G46 -> 1883.3866
A47: 46 | B47: =MAX(0,I46) -> 6300.4666 | C47: =IF(B47<=0,0,IF(A47='Loan Calculator'!B12,MIN('Loan Calculator'!B11,B47),0)+IF(A47='Loan Calculator'!B14,MIN('Loan Calculator'!B13,B47),0)) -> 0 | D47: =IF(B47<=0,0,'Loan Calculator'!B4) -> 365.72 | E47: =IF(B47<=0,0,IF(A47>='Loan Calculator'!B18,'Loan Calculator'!B17,0)+IF(A47>='Loan Calculator'!B20,'Loan Calculator'!B19,0)+IF(A47>='Loan Calculator'!B22,'Loan Calculator'!B21,0)) -> 197.44 | F47: =IF(B47<=0,0,MIN(D47+E47,(B47-C47)*(1+'Loan Calculator'!B7))) -> 563.16 | G47: =IF(B47<=0,0,MAX(0,(B47-C47)*'Loan Calculator'!B7)) -> 14.539538 | H47: =IF(B47<=0,0,F47-G47) -> 548.62046 | I47: =IF(B47<=0,0,MAX(0,B47-C47-H47)) -> 5751.8462 | J47: =J46+G47 -> 1897.9262
A48: 47 | B48: =MAX(0,I47) -> 5751.8462 | C48: =IF(B48<=0,0,IF(A48='Loan Calculator'!B12,MIN('Loan Calculator'!B11,B48),0)+IF(A48='Loan Calculator'!B14,MIN('Loan Calculator'!B13,B48),0)) -> 0 | D48: =IF(B48<=0,0,'Loan Calculator'!B4) -> 365.72 | E48: =IF(B48<=0,0,IF(A48>='Loan Calculator'!B18,'Loan Calculator'!B17,0)+IF(A48>='Loan Calculator'!B20,'Loan Calculator'!B19,0)+IF(A48>='Loan Calculator'!B22,'Loan Calculator'!B21,0)) -> 197.44 | F48: =IF(B48<=0,0,MIN(D48+E48,(B48-C48)*(1+'Loan Calculator'!B7))) -> 563.16 | G48: =IF(B48<=0,0,MAX(0,(B48-C48)*'Loan Calculator'!B7)) -> 13.273491 | H48: =IF(B48<=0,0,F48-G48) -> 549.88651 | I48: =IF(B48<=0,0,MAX(0,B48-C48-H48)) -> 5201.9597 | J48: =J47+G48 -> 1911.1997
A49: 48 | B49: =MAX(0,I48) -> 5201.9597 | C49: =IF(B49<=0,0,IF(A49='Loan Calculator'!B12,MIN('Loan Calculator'!B11,B49),0)+IF(A49='Loan Calculator'!B14,MIN('Loan Calculator'!B13,B49),0)) -> 0 | D49: =IF(B49<=0,0,'Loan Calculator'!B4) -> 365.72 | E49: =IF(B49<=0,0,IF(A49>='Loan Calculator'!B18,'Loan Calculator'!B17,0)+IF(A49>='Loan Calculator'!B20,'Loan Calculator'!B19,0)+IF(A49>='Loan Calculator'!B22,'Loan Calculator'!B21,0)) -> 197.44 | F49: =IF(B49<=0,0,MIN(D49+E49,(B49-C49)*(1+'Loan Calculator'!B7))) -> 563.16 | G49: =IF(B49<=0,0,MAX(0,(B49-C49)*'Loan Calculator'!B7)) -> 12.004522 | H49: =IF(B49<=0,0,F49-G49) -> 551.15548 | I49: =IF(B49<=0,0,MAX(0,B49-C49-H49)) -> 4650.8042 | J49: =J48+G49 -> 1923.2042
A50: 49 | B50: =MAX(0,I49) -> 4650.8042 | C50: =IF(B50<=0,0,IF(A50='Loan Calculator'!B12,MIN('Loan Calculator'!B11,B50),0)+IF(A50='Loan Calculator'!B14,MIN('Loan Calculator'!B13,B50),0)) -> 0 | D50: =IF(B50<=0,0,'Loan Calculator'!B4) -> 365.72 | E50: =IF(B50<=0,0,IF(A50>='Loan Calculator'!B18,'Loan Calculator'!B17,0)+IF(A50>='Loan Calculator'!B20,'Loan Calculator'!B19,0)+IF(A50>='Loan Calculator'!B22,'Loan Calculator'!B21,0)) -> 197.44 | F50: =IF(B50<=0,0,MIN(D50+E50,(B50-C50)*(1+'Loan Calculator'!B7))) -> 563.16 | G50: =IF(B50<=0,0,MAX(0,(B50-C50)*'Loan Calculator'!B7)) -> 10.732625 | H50: =IF(B50<=0,0,F50-G50) -> 552.42737 | I50: =IF(B50<=0,0,MAX(0,B50-C50-H50)) -> 4098.3768 | J50: =J49+G50 -> 1933.9368
A51: 50 | B51: =MAX(0,I50) -> 4098.3768 | C51: =IF(B51<=0,0,IF(A51='Loan Calculator'!B12,MIN('Loan Calculator'!B11,B51),0)+IF(A51='Loan Calculator'!B14,MIN('Loan Calculator'!B13,B51),0)) -> 0 | D51: =IF(B51<=0,0,'Loan Calculator'!B4) -> 365.72 | E51: =IF(B51<=0,0,IF(A51>='Loan Calculator'!B18,'Loan Calculator'!B17,0)+IF(A51>='Loan Calculator'!B20,'Loan Calculator'!B19,0)+IF(A51>='Loan Calculator'!B22,'Loan Calculator'!B21,0)) -> 197.44 | F51: =IF(B51<=0,0,MIN(D51+E51,(B51-C51)*(1+'Loan Calculator'!B7))) -> 563.16 | G51: =IF(B51<=0,0,MAX(0,(B51-C51)*'Loan Calculator'!B7)) -> 9.4577926 | H51: =IF(B51<=0,0,F51-G51) -> 553.70221 | I51: =IF(B51<=0,0,MAX(0,B51-C51-H51)) -> 3544.6746 | J51: =J50+G51 -> 1943.3946
A52: 51 | B52: =MAX(0,I51) -> 3544.6746 | C52: =IF(B52<=0,0,IF(A52='Loan Calculator'!B12,MIN('Loan Calculator'!B11,B52),0)+IF(A52='Loan Calculator'!B14,MIN('Loan Calculator'!B13,B52),0)) -> 0 | D52: =IF(B52<=0,0,'Loan Calculator'!B4) -> 365.72 | E52: =IF(B52<=0,0,IF(A52>='Loan Calculator'!B18,'Loan Calculator'!B17,0)+IF(A52>='Loan Calculator'!B20,'Loan Calculator'!B19,0)+IF(A52>='Loan Calculator'!B22,'Loan Calculator'!B21,0)) -> 197.44 | F52: =IF(B52<=0,0,MIN(D52+E52,(B52-C52)*(1+'Loan Calculator'!B7))) -> 563.16 | G52: =IF(B52<=0,0,MAX(0,(B52-C52)*'Loan Calculator'!B7)) -> 8.1800183 | H52: =IF(B52<=0,0,F52-G52) -> 554.97998 | I52: =IF(B52<=0,0,MAX(0,B52-C52-H52)) -> 2989.6946 | J52: =J51+G52 -> 1951.5746
A53: 52 | B53: =MAX(0,I52) -> 2989.6946 | C53: =IF(B53<=0,0,IF(A53='Loan Calculator'!B12,MIN('Loan Calculator'!B11,B53),0)+IF(A53='Loan Calculator'!B14,MIN('Loan Calculator'!B13,B53),0)) -> 0 | D53: =IF(B53<=0,0,'Loan Calculator'!B4) -> 365.72 | E53: =IF(B53<=0,0,IF(A53>='Loan Calculator'!B18,'Loan Calculator'!B17,0)+IF(A53>='Loan Calculator'!B20,'Loan Calculator'!B19,0)+IF(A53>='Loan Calculator'!B22,'Loan Calculator'!B21,0)) -> 197.44 | F53: =IF(B53<=0,0,MIN(D53+E53,(B53-C53)*(1+'Loan Calculator'!B7))) -> 563.16 | G53: =IF(B53<=0,0,MAX(0,(B53-C53)*'Loan Calculator'!B7)) -> 6.8992953 | H53: =IF(B53<=0,0,F53-G53) -> 556.2607 | I53: =IF(B53<=0,0,MAX(0,B53-C53-H53)) -> 2433.4339 | J53: =J52+G53 -> 1958.4739
A54: 53 | B54: =MAX(0,I53) -> 2433.4339 | C54: =IF(B54<=0,0,IF(A54='Loan Calculator'!B12,MIN('Loan Calculator'!B11,B54),0)+IF(A54='Loan Calculator'!B14,MIN('Loan Calculator'!B13,B54),0)) -> 0 | D54: =IF(B54<=0,0,'Loan Calculator'!B4) -> 365.72 | E54: =IF(B54<=0,0,IF(A54>='Loan Calculator'!B18,'Loan Calculator'!B17,0)+IF(A54>='Loan Calculator'!B20,'Loan Calculator'!B19,0)+IF(A54>='Loan Calculator'!B22,'Loan Calculator'!B21,0)) -> 197.44 | F54: =IF(B54<=0,0,MIN(D54+E54,(B54-C54)*(1+'Loan Calculator'!B7))) -> 563.16 | G54: =IF(B54<=0,0,MAX(0,(B54-C54)*'Loan Calculator'!B7)) -> 5.6156167 | H54: =IF(B54<=0,0,F54-G54) -> 557.54438 | I54: =IF(B54<=0,0,MAX(0,B54-C54-H54)) -> 1875.8895 | J54: =J53+G54 -> 1964.0895
A55: 54 | B55: =MAX(0,I54) -> 1875.8895 | C55: =IF(B55<=0,0,IF(A55='Loan Calculator'!B12,MIN('Loan Calculator'!B11,B55),0)+IF(A55='Loan Calculator'!B14,MIN('Loan Calculator'!B13,B55),0)) -> 0 | D55: =IF(B55<=0,0,'Loan Calculator'!B4) -> 365.72 | E55: =IF(B55<=0,0,IF(A55>='Loan Calculator'!B18,'Loan Calculator'!B17,0)+IF(A55>='Loan Calculator'!B20,'Loan Calculator'!B19,0)+IF(A55>='Loan Calculator'!B22,'Loan Calculator'!B21,0)) -> 197.44 | F55: =IF(B55<=0,0,MIN(D55+E55,(B55-C55)*(1+'Loan Calculator'!B7))) -> 563.16 | G55: =IF(B55<=0,0,MAX(0,(B55-C55)*'Loan Calculator'!B7)) -> 4.3289758 | H55: =IF(B55<=0,0,F55-G55) -> 558.83102 | I55: =IF(B55<=0,0,MAX(0,B55-C55-H55)) -> 1317.0585 | J55: =J54+G55 -> 1968.4185
A56: 55 | B56: =MAX(0,I55) -> 1317.0585 | C56: =IF(B56<=0,0,IF(A56='Loan Calculator'!B12,MIN('Loan Calculator'!B11,B56),0)+IF(A56='Loan Calculator'!B14,MIN('Loan Calculator'!B13,B56),0)) -> 0 | D56: =IF(B56<=0,0,'Loan Calculator'!B4) -> 365.72 | E56: =IF(B56<=0,0,IF(A56>='Loan Calculator'!B18,'Loan Calculator'!B17,0)+IF(A56>='Loan Calculator'!B20,'Loan Calculator'!B19,0)+IF(A56>='Loan Calculator'!B22,'Loan Calculator'!B21,0)) -> 197.44 | F56: =IF(B56<=0,0,MIN(D56+E56,(B56-C56)*(1+'Loan Calculator'!B7))) -> 563.16 | G56: =IF(B56<=0,0,MAX(0,(B56-C56)*'Loan Calculator'!B7)) -> 3.0393658 | H56: =IF(B56<=0,0,F56-G56) -> 560.12063 | I56: =IF(B56<=0,0,MAX(0,B56-C56-H56)) -> 756.93787 | J56: =J55+G56 -> 1971.4579
A57: 56 | B57: =MAX(0,I56) -> 756.93787 | C57: =IF(B57<=0,0,IF(A57='Loan Calculator'!B12,MIN('Loan Calculator'!B11,B57),0)+IF(A57='Loan Calculator'!B14,MIN('Loan Calculator'!B13,B57),0)) -> 0 | D57: =IF(B57<=0,0,'Loan Calculator'!B4) -> 365.72 | E57: =IF(B57<=0,0,IF(A57>='Loan Calculator'!B18,'Loan Calculator'!B17,0)+IF(A57>='Loan Calculator'!B20,'Loan Calculator'!B19,0)+IF(A57>='Loan Calculator'!B22,'Loan Calculator'!B21,0)) -> 197.44 | F57: =IF(B57<=0,0,MIN(D57+E57,(B57-C57)*(1+'Loan Calculator'!B7))) -> 563.16 | G57: =IF(B57<=0,0,MAX(0,(B57-C57)*'Loan Calculator'!B7)) -> 1.7467797 | H57: =IF(B57<=0,0,F57-G57) -> 561.41322 | I57: =IF(B57<=0,0,MAX(0,B57-C57-H57)) -> 195.52465 | J57: =J56+G57 -> 1973.2047
A58: 57 | B58: =MAX(0,I57) -> 195.52465 | C58: =IF(B58<=0,0,IF(A58='Loan Calculator'!B12,MIN('Loan Calculator'!B11,B58),0)+IF(A58='Loan Calculator'!B14,MIN('Loan Calculator'!B13,B58),0)) -> 0 | D58: =IF(B58<=0,0,'Loan Calculator'!B4) -> 365.72 | E58: =IF(B58<=0,0,IF(A58>='Loan Calculator'!B18,'Loan Calculator'!B17,0)+IF(A58>='Loan Calculator'!B20,'Loan Calculator'!B19,0)+IF(A58>='Loan Calculator'!B22,'Loan Calculator'!B21,0)) -> 197.44 | F58: =IF(B58<=0,0,MIN(D58+E58,(B58-C58)*(1+'Loan Calculator'!B7))) -> 195.97586 | G58: =IF(B58<=0,0,MAX(0,(B58-C58)*'Loan Calculator'!B7)) -> 0.45121073 | H58: =IF(B58<=0,0,F58-G58) -> 195.52465 | I58: =IF(B58<=0,0,MAX(0,B58-C58-H58)) -> 0 | J58: =J57+G58 -> 1973.6559
A59: 58 | B59: =MAX(0,I58) -> 0 | C59: =IF(B59<=0,0,IF(A59='Loan Calculator'!B12,MIN('Loan Calculator'!B11,B59),0)+IF(A59='Loan Calculator'!B14,MIN('Loan Calculator'!B13,B59),0)) -> 0 | D59: =IF(B59<=0,0,'Loan Calculator'!B4) -> 0 | E59: =IF(B59<=0,0,IF(A59>='Loan Calculator'!B18,'Loan Calculator'!B17,0)+IF(A59>='Loan Calculator'!B20,'Loan Calculator'!B19,0)+IF(A59>='Loan Calculator'!B22,'Loan Calculator'!B21,0)) -> 0 | F59: =IF(B59<=0,0,MIN(D59+E59,(B59-C59)*(1+'Loan Calculator'!B7))) -> 0 | G59: =IF(B59<=0,0,MAX(0,(B59-C59)*'Loan Calculator'!B7)) -> 0 | H59: =IF(B59<=0,0,F59-G59) -> 0 | I59: =IF(B59<=0,0,MAX(0,B59-C59-H59)) -> 0 | J59: =J58+G59 -> 1973.6559
A60: 59 | B60: =MAX(0,I59) -> 0 | C60: =IF(B60<=0,0,IF(A60='Loan Calculator'!B12,MIN('Loan Calculator'!B11,B60),0)+IF(A60='Loan Calculator'!B14,MIN('Loan Calculator'!B13,B60),0)) -> 0 | D60: =IF(B60<=0,0,'Loan Calculator'!B4) -> 0 | E60: =IF(B60<=0,0,IF(A60>='Loan Calculator'!B18,'Loan Calculator'!B17,0)+IF(A60>='Loan Calculator'!B20,'Loan Calculator'!B19,0)+IF(A60>='Loan Calculator'!B22,'Loan Calculator'!B21,0)) -> 0 | F60: =IF(B60<=0,0,MIN(D60+E60,(B60-C60)*(1+'Loan Calculator'!B7))) -> 0 | G60: =IF(B60<=0,0,MAX(0,(B60-C60)*'Loan Calculator'!B7)) -> 0 | H60: =IF(B60<=0,0,F60-G60) -> 0 | I60: =IF(B60<=0,0,MAX(0,B60-C60-H60)) -> 0 | J60: =J59+G60 -> 1973.6559
A61: 60 | B61: =MAX(0,I60) -> 0 | C61: =IF(B61<=0,0,IF(A61='Loan Calculator'!B12,MIN('Loan Calculator'!B11,B61),0)+IF(A61='Loan Calculator'!B14,MIN('Loan Calculator'!B13,B61),0)) -> 0 | D61: =IF(B61<=0,0,'Loan Calculator'!B4) -> 0 | E61: =IF(B61<=0,0,IF(A61>='Loan Calculator'!B18,'Loan Calculator'!B17,0)+IF(A61>='Loan Calculator'!B20,'Loan Calculator'!B19,0)+IF(A61>='Loan Calculator'!B22,'Loan Calculator'!B21,0)) -> 0 | F61: =IF(B61<=0,0,MIN(D61+E61,(B61-C61)*(1+'Loan Calculator'!B7))) -> 0 | G61: =IF(B61<=0,0,MAX(0,(B61-C61)*'Loan Calculator'!B7)) -> 0 | H61: =IF(B61<=0,0,F61-G61) -> 0 | I61: =IF(B61<=0,0,MAX(0,B61-C61-H61)) -> 0 | J61: =J60+G61 -> 1973.6559
A62: 61 | B62: =MAX(0,I61) -> 0 | C62: =IF(B62<=0,0,IF(A62='Loan Calculator'!B12,MIN('Loan Calculator'!B11,B62),0)+IF(A62='Loan Calculator'!B14,MIN('Loan Calculator'!B13,B62),0)) -> 0 | D62: =IF(B62<=0,0,'Loan Calculator'!B4) -> 0 | E62: =IF(B62<=0,0,IF(A62>='Loan Calculator'!B18,'Loan Calculator'!B17,0)+IF(A62>='Loan Calculator'!B20,'Loan Calculator'!B19,0)+IF(A62>='Loan Calculator'!B22,'Loan Calculator'!B21,0)) -> 0 | F62: =IF(B62<=0,0,MIN(D62+E62,(B62-C62)*(1+'Loan Calculator'!B7))) -> 0 | G62: =IF(B62<=0,0,MAX(0,(B62-C62)*'Loan Calculator'!B7)) -> 0 | H62: =IF(B62<=0,0,F62-G62) -> 0 | I62: =IF(B62<=0,0,MAX(0,B62-C62-H62)) -> 0 | J62: =J61+G62 -> 1973.6559
A63: 62 | B63: =MAX(0,I62) -> 0 | C63: =IF(B63<=0,0,IF(A63='Loan Calculator'!B12,MIN('Loan Calculator'!B11,B63),0)+IF(A63='Loan Calculator'!B14,MIN('Loan Calculator'!B13,B63),0)) -> 0 | D63: =IF(B63<=0,0,'Loan Calculator'!B4) -> 0 | E63: =IF(B63<=0,0,IF(A63>='Loan Calculator'!B18,'Loan Calculator'!B17,0)+IF(A63>='Loan Calculator'!B20,'Loan Calculator'!B19,0)+IF(A63>='Loan Calculator'!B22,'Loan Calculator'!B21,0)) -> 0 | F63: =IF(B63<=0,0,MIN(D63+E63,(B63-C63)*(1+'Loan Calculator'!B7))) -> 0 | G63: =IF(B63<=0,0,MAX(0,(B63-C63)*'Loan Calculator'!B7)) -> 0 | H63: =IF(B63<=0,0,F63-G63) -> 0 | I63: =IF(B63<=0,0,MAX(0,B63-C63-H63)) -> 0 | J63: =J62+G63 -> 1973.6559
A64: 63 | B64: =MAX(0,I63) -> 0 | C64: =IF(B64<=0,0,IF(A64='Loan Calculator'!B12,MIN('Loan Calculator'!B11,B64),0)+IF(A64='Loan Calculator'!B14,MIN('Loan Calculator'!B13,B64),0)) -> 0 | D64: =IF(B64<=0,0,'Loan Calculator'!B4) -> 0 | E64: =IF(B64<=0,0,IF(A64>='Loan Calculator'!B18,'Loan Calculator'!B17,0)+IF(A64>='Loan Calculator'!B20,'Loan Calculator'!B19,0)+IF(A64>='Loan Calculator'!B22,'Loan Calculator'!B21,0)) -> 0 | F64: =IF(B64<=0,0,MIN(D64+E64,(B64-C64)*(1+'Loan Calculator'!B7))) -> 0 | G64: =IF(B64<=0,0,MAX(0,(B64-C64)*'Loan Calculator'!B7)) -> 0 | H64: =IF(B64<=0,0,F64-G64) -> 0 | I64: =IF(B64<=0,0,MAX(0,B64-C64-H64)) -> 0 | J64: =J63+G64 -> 1973.6559
A65: 64 | B65: =MAX(0,I64) -> 0 | C65: =IF(B65<=0,0,IF(A65='Loan Calculator'!B12,MIN('Loan Calculator'!B11,B65),0)+IF(A65='Loan Calculator'!B14,MIN('Loan Calculator'!B13,B65),0)) -> 0 | D65: =IF(B65<=0,0,'Loan Calculator'!B4) -> 0 | E65: =IF(B65<=0,0,IF(A65>='Loan Calculator'!B18,'Loan Calculator'!B17,0)+IF(A65>='Loan Calculator'!B20,'Loan Calculator'!B19,0)+IF(A65>='Loan Calculator'!B22,'Loan Calculator'!B21,0)) -> 0 | F65: =IF(B65<=0,0,MIN(D65+E65,(B65-C65)*(1+'Loan Calculator'!B7))) -> 0 | G65: =IF(B65<=0,0,MAX(0,(B65-C65)*'Loan Calculator'!B7)) -> 0 | H65: =IF(B65<=0,0,F65-G65) -> 0 | I65: =IF(B65<=0,0,MAX(0,B65-C65-H65)) -> 0 | J65: =J64+G65 -> 1973.6559
A66: 65 | B66: =MAX(0,I65) -> 0 | C66: =IF(B66<=0,0,IF(A66='Loan Calculator'!B12,MIN('Loan Calculator'!B11,B66),0)+IF(A66='Loan Calculator'!B14,MIN('Loan Calculator'!B13,B66),0)) -> 0 | D66: =IF(B66<=0,0,'Loan Calculator'!B4) -> 0 | E66: =IF(B66<=0,0,IF(A66>='Loan Calculator'!B18,'Loan Calculator'!B17,0)+IF(A66>='Loan Calculator'!B20,'Loan Calculator'!B19,0)+IF(A66>='Loan Calculator'!B22,'Loan Calculator'!B21,0)) -> 0 | F66: =IF(B66<=0,0,MIN(D66+E66,(B66-C66)*(1+'Loan Calculator'!B7))) -> 0 | G66: =IF(B66<=0,0,MAX(0,(B66-C66)*'Loan Calculator'!B7)) -> 0 | H66: =IF(B66<=0,0,F66-G66) -> 0 | I66: =IF(B66<=0,0,MAX(0,B66-C66-H66)) -> 0 | J66: =J65+G66 -> 1973.6559
A67: 66 | B67: =MAX(0,I66) -> 0 | C67: =IF(B67<=0,0,IF(A67='Loan Calculator'!B12,MIN('Loan Calculator'!B11,B67),0)+IF(A67='Loan Calculator'!B14,MIN('Loan Calculator'!B13,B67),0)) -> 0 | D67: =IF(B67<=0,0,'Loan Calculator'!B4) -> 0 | E67: =IF(B67<=0,0,IF(A67>='Loan Calculator'!B18,'Loan Calculator'!B17,0)+IF(A67>='Loan Calculator'!B20,'Loan Calculator'!B19,0)+IF(A67>='Loan Calculator'!B22,'Loan Calculator'!B21,0)) -> 0 | F67: =IF(B67<=0,0,MIN(D67+E67,(B67-C67)*(1+'Loan Calculator'!B7))) -> 0 | G67: =IF(B67<=0,0,MAX(0,(B67-C67)*'Loan Calculator'!B7)) -> 0 | H67: =IF(B67<=0,0,F67-G67) -> 0 | I67: =IF(B67<=0,0,MAX(0,B67-C67-H67)) -> 0 | J67: =J66+G67 -> 1973.6559
A68: 67 | B68: =MAX(0,I67) -> 0 | C68: =IF(B68<=0,0,IF(A68='Loan Calculator'!B12,MIN('Loan Calculator'!B11,B68),0)+IF(A68='Loan Calculator'!B14,MIN('Loan Calculator'!B13,B68),0)) -> 0 | D68: =IF(B68<=0,0,'Loan Calculator'!B4) -> 0 | E68: =IF(B68<=0,0,IF(A68>='Loan Calculator'!B18,'Loan Calculator'!B17,0)+IF(A68>='Loan Calculator'!B20,'Loan Calculator'!B19,0)+IF(A68>='Loan Calculator'!B22,'Loan Calculator'!B21,0)) -> 0 | F68: =IF(B68<=0,0,MIN(D68+E68,(B68-C68)*(1+'Loan Calculator'!B7))) -> 0 | G68: =IF(B68<=0,0,MAX(0,(B68-C68)*'Loan Calculator'!B7)) -> 0 | H68: =IF(B68<=0,0,F68-G68) -> 0 | I68: =IF(B68<=0,0,MAX(0,B68-C68-H68)) -> 0 | J68: =J67+G68 -> 1973.6559
A69: 68 | B69: =MAX(0,I68) -> 0 | C69: =IF(B69<=0,0,IF(A69='Loan Calculator'!B12,MIN('Loan Calculator'!B11,B69),0)+IF(A69='Loan Calculator'!B14,MIN('Loan Calculator'!B13,B69),0)) -> 0 | D69: =IF(B69<=0,0,'Loan Calculator'!B4) -> 0 | E69: =IF(B69<=0,0,IF(A69>='Loan Calculator'!B18,'Loan Calculator'!B17,0)+IF(A69>='Loan Calculator'!B20,'Loan Calculator'!B19,0)+IF(A69>='Loan Calculator'!B22,'Loan Calculator'!B21,0)) -> 0 | F69: =IF(B69<=0,0,MIN(D69+E69,(B69-C69)*(1+'Loan Calculator'!B7))) -> 0 | G69: =IF(B69<=0,0,MAX(0,(B69-C69)*'Loan Calculator'!B7)) -> 0 | H69: =IF(B69<=0,0,F69-G69) -> 0 | I69: =IF(B69<=0,0,MAX(0,B69-C69-H69)) -> 0 | J69: =J68+G69 -> 1973.6559
A70: 69 | B70: =MAX(0,I69) -> 0 | C70: =IF(B70<=0,0,IF(A70='Loan Calculator'!B12,MIN('Loan Calculator'!B11,B70),0)+IF(A70='Loan Calculator'!B14,MIN('Loan Calculator'!B13,B70),0)) -> 0 | D70: =IF(B70<=0,0,'Loan Calculator'!B4) -> 0 | E70: =IF(B70<=0,0,IF(A70>='Loan Calculator'!B18,'Loan Calculator'!B17,0)+IF(A70>='Loan Calculator'!B20,'Loan Calculator'!B19,0)+IF(A70>='Loan Calculator'!B22,'Loan Calculator'!B21,0)) -> 0 | F70: =IF(B70<=0,0,MIN(D70+E70,(B70-C70)*(1+'Loan Calculator'!B7))) -> 0 | G70: =IF(B70<=0,0,MAX(0,(B70-C70)*'Loan Calculator'!B7)) -> 0 | H70: =IF(B70<=0,0,F70-G70) -> 0 | I70: =IF(B70<=0,0,MAX(0,B70-C70-H70)) -> 0 | J70: =J69+G70 -> 1973.6559
A71: 70 | B71: =MAX(0,I70) -> 0 | C71: =IF(B71<=0,0,IF(A71='Loan Calculator'!B12,MIN('Loan Calculator'!B11,B71),0)+IF(A71='Loan Calculator'!B14,MIN('Loan Calculator'!B13,B71),0)) -> 0 | D71: =IF(B71<=0,0,'Loan Calculator'!B4) -> 0 | E71: =IF(B71<=0,0,IF(A71>='Loan Calculator'!B18,'Loan Calculator'!B17,0)+IF(A71>='Loan Calculator'!B20,'Loan Calculator'!B19,0)+IF(A71>='Loan Calculator'!B22,'Loan Calculator'!B21,0)) -> 0 | F71: =IF(B71<=0,0,MIN(D71+E71,(B71-C71)*(1+'Loan Calculator'!B7))) -> 0 | G71: =IF(B71<=0,0,MAX(0,(B71-C71)*'Loan Calculator'!B7)) -> 0 | H71: =IF(B71<=0,0,F71-G71) -> 0 | I71: =IF(B71<=0,0,MAX(0,B71-C71-H71)) -> 0 | J71: =J70+G71 -> 1973.6559
A72: 71 | B72: =MAX(0,I71) -> 0 | C72: =IF(B72<=0,0,IF(A72='Loan Calculator'!B12,MIN('Loan Calculator'!B11,B72),0)+IF(A72='Loan Calculator'!B14,MIN('Loan Calculator'!B13,B72),0)) -> 0 | D72: =IF(B72<=0,0,'Loan Calculator'!B4) -> 0 | E72: =IF(B72<=0,0,IF(A72>='Loan Calculator'!B18,'Loan Calculator'!B17,0)+IF(A72>='Loan Calculator'!B20,'Loan Calculator'!B19,0)+IF(A72>='Loan Calculator'!B22,'Loan Calculator'!B21,0)) -> 0 | F72: =IF(B72<=0,0,MIN(D72+E72,(B72-C72)*(1+'Loan Calculator'!B7))) -> 0 | G72: =IF(B72<=0,0,MAX(0,(B72-C72)*'Loan Calculator'!B7)) -> 0 | H72: =IF(B72<=0,0,F72-G72) -> 0 | I72: =IF(B72<=0,0,MAX(0,B72-C72-H72)) -> 0 | J72: =J71+G72 -> 1973.6559
A73: 72 | B73: =MAX(0,I72) -> 0 | C73: =IF(B73<=0,0,IF(A73='Loan Calculator'!B12,MIN('Loan Calculator'!B11,B73),0)+IF(A73='Loan Calculator'!B14,MIN('Loan Calculator'!B13,B73),0)) -> 0 | D73: =IF(B73<=0,0,'Loan Calculator'!B4) -> 0 | E73: =IF(B73<=0,0,IF(A73>='Loan Calculator'!B18,'Loan Calculator'!B17,0)+IF(A73>='Loan Calculator'!B20,'Loan Calculator'!B19,0)+IF(A73>='Loan Calculator'!B22,'Loan Calculator'!B21,0)) -> 0 | F73: =IF(B73<=0,0,MIN(D73+E73,(B73-C73)*(1+'Loan Calculator'!B7))) -> 0 | G73: =IF(B73<=0,0,MAX(0,(B73-C73)*'Loan Calculator'!B7)) -> 0 | H73: =IF(B73<=0,0,F73-G73) -> 0 | I73: =IF(B73<=0,0,MAX(0,B73-C73-H73)) -> 0 | J73: =J72+G73 -> 1973.6559
A74: 73 | B74: =MAX(0,I73) -> 0 | C74: =IF(B74<=0,0,IF(A74='Loan Calculator'!B12,MIN('Loan Calculator'!B11,B74),0)+IF(A74='Loan Calculator'!B14,MIN('Loan Calculator'!B13,B74),0)) -> 0 | D74: =IF(B74<=0,0,'Loan Calculator'!B4) -> 0 | E74: =IF(B74<=0,0,IF(A74>='Loan Calculator'!B18,'Loan Calculator'!B17,0)+IF(A74>='Loan Calculator'!B20,'Loan Calculator'!B19,0)+IF(A74>='Loan Calculator'!B22,'Loan Calculator'!B21,0)) -> 0 | F74: =IF(B74<=0,0,MIN(D74+E74,(B74-C74)*(1+'Loan Calculator'!B7))) -> 0 | G74: =IF(B74<=0,0,MAX(0,(B74-C74)*'Loan Calculator'!B7)) -> 0 | H74: =IF(B74<=0,0,F74-G74) -> 0 | I74: =IF(B74<=0,0,MAX(0,B74-C74-H74)) -> 0 | J74: =J73+G74 -> 1973.6559
A75: 74 | B75: =MAX(0,I74) -> 0 | C75: =IF(B75<=0,0,IF(A75='Loan Calculator'!B12,MIN('Loan Calculator'!B11,B75),0)+IF(A75='Loan Calculator'!B14,MIN('Loan Calculator'!B13,B75),0)) -> 0 | D75: =IF(B75<=0,0,'Loan Calculator'!B4) -> 0 | E75: =IF(B75<=0,0,IF(A75>='Loan Calculator'!B18,'Loan Calculator'!B17,0)+IF(A75>='Loan Calculator'!B20,'Loan Calculator'!B19,0)+IF(A75>='Loan Calculator'!B22,'Loan Calculator'!B21,0)) -> 0 | F75: =IF(B75<=0,0,MIN(D75+E75,(B75-C75)*(1+'Loan Calculator'!B7))) -> 0 | G75: =IF(B75<=0,0,MAX(0,(B75-C75)*'Loan Calculator'!B7)) -> 0 | H75: =IF(B75<=0,0,F75-G75) -> 0 | I75: =IF(B75<=0,0,MAX(0,B75-C75-H75)) -> 0 | J75: =J74+G75 -> 1973.6559
A76: 75 | B76: =MAX(0,I75) -> 0 | C76: =IF(B76<=0,0,IF(A76='Loan Calculator'!B12,MIN('Loan Calculator'!B11,B76),0)+IF(A76='Loan Calculator'!B14,MIN('Loan Calculator'!B13,B76),0)) -> 0 | D76: =IF(B76<=0,0,'Loan Calculator'!B4) -> 0 | E76: =IF(B76<=0,0,IF(A76>='Loan Calculator'!B18,'Loan Calculator'!B17,0)+IF(A76>='Loan Calculator'!B20,'Loan Calculator'!B19,0)+IF(A76>='Loan Calculator'!B22,'Loan Calculator'!B21,0)) -> 0 | F76: =IF(B76<=0,0,MIN(D76+E76,(B76-C76)*(1+'Loan Calculator'!B7))) -> 0 | G76: =IF(B76<=0,0,MAX(0,(B76-C76)*'Loan Calculator'!B7)) -> 0 | H76: =IF(B76<=0,0,F76-G76) -> 0 | I76: =IF(B76<=0,0,MAX(0,B76-C76-H76)) -> 0 | J76: =J75+G76 -> 1973.6559
A77: 76 | B77: =MAX(0,I76) -> 0 | C77: =IF(B77<=0,0,IF(A77='Loan Calculator'!B12,MIN('Loan Calculator'!B11,B77),0)+IF(A77='Loan Calculator'!B14,MIN('Loan Calculator'!B13,B77),0)) -> 0 | D77: =IF(B77<=0,0,'Loan Calculator'!B4) -> 0 | E77: =IF(B77<=0,0,IF(A77>='Loan Calculator'!B18,'Loan Calculator'!B17,0)+IF(A77>='Loan Calculator'!B20,'Loan Calculator'!B19,0)+IF(A77>='Loan Calculator'!B22,'Loan Calculator'!B21,0)) -> 0 | F77: =IF(B77<=0,0,MIN(D77+E77,(B77-C77)*(1+'Loan Calculator'!B7))) -> 0 | G77: =IF(B77<=0,0,MAX(0,(B77-C77)*'Loan Calculator'!B7)) -> 0 | H77: =IF(B77<=0,0,F77-G77) -> 0 | I77: =IF(B77<=0,0,MAX(0,B77-C77-H77)) -> 0 | J77: =J76+G77 -> 1973.6559
A78: 77 | B78: =MAX(0,I77) -> 0 | C78: =IF(B78<=0,0,IF(A78='Loan Calculator'!B12,MIN('Loan Calculator'!B11,B78),0)+IF(A78='Loan Calculator'!B14,MIN('Loan Calculator'!B13,B78),0)) -> 0 | D78: =IF(B78<=0,0,'Loan Calculator'!B4) -> 0 | E78: =IF(B78<=0,0,IF(A78>='Loan Calculator'!B18,'Loan Calculator'!B17,0)+IF(A78>='Loan Calculator'!B20,'Loan Calculator'!B19,0)+IF(A78>='Loan Calculator'!B22,'Loan Calculator'!B21,0)) -> 0 | F78: =IF(B78<=0,0,MIN(D78+E78,(B78-C78)*(1+'Loan Calculator'!B7))) -> 0 | G78: =IF(B78<=0,0,MAX(0,(B78-C78)*'Loan Calculator'!B7)) -> 0 | H78: =IF(B78<=0,0,F78-G78) -> 0 | I78: =IF(B78<=0,0,MAX(0,B78-C78-H78)) -> 0 | J78: =J77+G78 -> 1973.6559
A79: 78 | B79: =MAX(0,I78) -> 0 | C79: =IF(B79<=0,0,IF(A79='Loan Calculator'!B12,MIN('Loan Calculator'!B11,B79),0)+IF(A79='Loan Calculator'!B14,MIN('Loan Calculator'!B13,B79),0)) -> 0 | D79: =IF(B79<=0,0,'Loan Calculator'!B4) -> 0 | E79: =IF(B79<=0,0,IF(A79>='Loan Calculator'!B18,'Loan Calculator'!B17,0)+IF(A79>='Loan Calculator'!B20,'Loan Calculator'!B19,0)+IF(A79>='Loan Calculator'!B22,'Loan Calculator'!B21,0)) -> 0 | F79: =IF(B79<=0,0,MIN(D79+E79,(B79-C79)*(1+'Loan Calculator'!B7))) -> 0 | G79: =IF(B79<=0,0,MAX(0,(B79-C79)*'Loan Calculator'!B7)) -> 0 | H79: =IF(B79<=0,0,F79-G79) -> 0 | I79: =IF(B79<=0,0,MAX(0,B79-C79-H79)) -> 0 | J79: =J78+G79 -> 1973.6559
A80: 79 | B80: =MAX(0,I79) -> 0 | C80: =IF(B80<=0,0,IF(A80='Loan Calculator'!B12,MIN('Loan Calculator'!B11,B80),0)+IF(A80='Loan Calculator'!B14,MIN('Loan Calculator'!B13,B80),0)) -> 0 | D80: =IF(B80<=0,0,'Loan Calculator'!B4) -> 0 | E80: =IF(B80<=0,0,IF(A80>='Loan Calculator'!B18,'Loan Calculator'!B17,0)+IF(A80>='Loan Calculator'!B20,'Loan Calculator'!B19,0)+IF(A80>='Loan Calculator'!B22,'Loan Calculator'!B21,0)) -> 0 | F80: =IF(B80<=0,0,MIN(D80+E80,(B80-C80)*(1+'Loan Calculator'!B7))) -> 0 | G80: =IF(B80<=0,0,MAX(0,(B80-C80)*'Loan Calculator'!B7)) -> 0 | H80: =IF(B80<=0,0,F80-G80) -> 0 | I80: =IF(B80<=0,0,MAX(0,B80-C80-H80)) -> 0 | J80: =J79+G80 -> 1973.6559
A81: 80 | B81: =MAX(0,I80) -> 0 | C81: =IF(B81<=0,0,IF(A81='Loan Calculator'!B12,MIN('Loan Calculator'!B11,B81),0)+IF(A81='Loan Calculator'!B14,MIN('Loan Calculator'!B13,B81),0)) -> 0 | D81: =IF(B81<=0,0,'Loan Calculator'!B4) -> 0 | E81: =IF(B81<=0,0,IF(A81>='Loan Calculator'!B18,'Loan Calculator'!B17,0)+IF(A81>='Loan Calculator'!B20,'Loan Calculator'!B19,0)+IF(A81>='Loan Calculator'!B22,'Loan Calculator'!B21,0)) -> 0 | F81: =IF(B81<=0,0,MIN(D81+E81,(B81-C81)*(1+'Loan Calculator'!B7))) -> 0 | G81: =IF(B81<=0,0,MAX(0,(B81-C81)*'Loan Calculator'!B7)) -> 0 | H81: =IF(B81<=0,0,F81-G81) -> 0 | I81: =IF(B81<=0,0,MAX(0,B81-C81-H81)) -> 0 | J81: =J80+G81 -> 1973.6559
A82: 81 | B82: =MAX(0,I81) -> 0 | C82: =IF(B82<=0,0,IF(A82='Loan Calculator'!B12,MIN('Loan Calculator'!B11,B82),0)+IF(A82='Loan Calculator'!B14,MIN('Loan Calculator'!B13,B82),0)) -> 0 | D82: =IF(B82<=0,0,'Loan Calculator'!B4) -> 0 | E82: =IF(B82<=0,0,IF(A82>='Loan Calculator'!B18,'Loan Calculator'!B17,0)+IF(A82>='Loan Calculator'!B20,'Loan Calculator'!B19,0)+IF(A82>='Loan Calculator'!B22,'Loan Calculator'!B21,0)) -> 0 | F82: =IF(B82<=0,0,MIN(D82+E82,(B82-C82)*(1+'Loan Calculator'!B7))) -> 0 | G82: =IF(B82<=0,0,MAX(0,(B82-C82)*'Loan Calculator'!B7)) -> 0 | H82: =IF(B82<=0,0,F82-G82) -> 0 | I82: =IF(B82<=0,0,MAX(0,B82-C82-H82)) -> 0 | J82: =J81+G82 -> 1973.6559
A83: 82 | B83: =MAX(0,I82) -> 0 | C83: =IF(B83<=0,0,IF(A83='Loan Calculator'!B12,MIN('Loan Calculator'!B11,B83),0)+IF(A83='Loan Calculator'!B14,MIN('Loan Calculator'!B13,B83),0)) -> 0 | D83: =IF(B83<=0,0,'Loan Calculator'!B4) -> 0 | E83: =IF(B83<=0,0,IF(A83>='Loan Calculator'!B18,'Loan Calculator'!B17,0)+IF(A83>='Loan Calculator'!B20,'Loan Calculator'!B19,0)+IF(A83>='Loan Calculator'!B22,'Loan Calculator'!B21,0)) -> 0 | F83: =IF(B83<=0,0,MIN(D83+E83,(B83-C83)*(1+'Loan Calculator'!B7))) -> 0 | G83: =IF(B83<=0,0,MAX(0,(B83-C83)*'Loan Calculator'!B7)) -> 0 | H83: =IF(B83<=0,0,F83-G83) -> 0 | I83: =IF(B83<=0,0,MAX(0,B83-C83-H83)) -> 0 | J83: =J82+G83 -> 1973.6559
A84: 83 | B84: =MAX(0,I83) -> 0 | C84: =IF(B84<=0,0,IF(A84='Loan Calculator'!B12,MIN('Loan Calculator'!B11,B84),0)+IF(A84='Loan Calculator'!B14,MIN('Loan Calculator'!B13,B84),0)) -> 0 | D84: =IF(B84<=0,0,'Loan Calculator'!B4) -> 0 | E84: =IF(B84<=0,0,IF(A84>='Loan Calculator'!B18,'Loan Calculator'!B17,0)+IF(A84>='Loan Calculator'!B20,'Loan Calculator'!B19,0)+IF(A84>='Loan Calculator'!B22,'Loan Calculator'!B21,0)) -> 0 | F84: =IF(B84<=0,0,MIN(D84+E84,(B84-C84)*(1+'Loan Calculator'!B7))) -> 0 | G84: =IF(B84<=0,0,MAX(0,(B84-C84)*'Loan Calculator'!B7)) -> 0 | H84: =IF(B84<=0,0,F84-G84) -> 0 | I84: =IF(B84<=0,0,MAX(0,B84-C84-H84)) -> 0 | J84: =J83+G84 -> 1973.6559
A85: 84 | B85: =MAX(0,I84) -> 0 | C85: =IF(B85<=0,0,IF(A85='Loan Calculator'!B12,MIN('Loan Calculator'!B11,B85),0)+IF(A85='Loan Calculator'!B14,MIN('Loan Calculator'!B13,B85),0)) -> 0 | D85: =IF(B85<=0,0,'Loan Calculator'!B4) -> 0 | E85: =IF(B85<=0,0,IF(A85>='Loan Calculator'!B18,'Loan Calculator'!B17,0)+IF(A85>='Loan Calculator'!B20,'Loan Calculator'!B19,0)+IF(A85>='Loan Calculator'!B22,'Loan Calculator'!B21,0)) -> 0 | F85: =IF(B85<=0,0,MIN(D85+E85,(B85-C85)*(1+'Loan Calculator'!B7))) -> 0 | G85: =IF(B85<=0,0,MAX(0,(B85-C85)*'Loan Calculator'!B7)) -> 0 | H85: =IF(B85<=0,0,F85-G85) -> 0 | I85: =IF(B85<=0,0,MAX(0,B85-C85-H85)) -> 0 | J85: =J84+G85 -> 1973.6559
A86: 85 | B86: =MAX(0,I85) -> 0 | C86: =IF(B86<=0,0,IF(A86='Loan Calculator'!B12,MIN('Loan Calculator'!B11,B86),0)+IF(A86='Loan Calculator'!B14,MIN('Loan Calculator'!B13,B86),0)) -> 0 | D86: =IF(B86<=0,0,'Loan Calculator'!B4) -> 0 | E86: =IF(B86<=0,0,IF(A86>='Loan Calculator'!B18,'Loan Calculator'!B17,0)+IF(A86>='Loan Calculator'!B20,'Loan Calculator'!B19,0)+IF(A86>='Loan Calculator'!B22,'Loan Calculator'!B21,0)) -> 0 | F86: =IF(B86<=0,0,MIN(D86+E86,(B86-C86)*(1+'Loan Calculator'!B7))) -> 0 | G86: =IF(B86<=0,0,MAX(0,(B86-C86)*'Loan Calculator'!B7)) -> 0 | H86: =IF(B86<=0,0,F86-G86) -> 0 | I86: =IF(B86<=0,0,MAX(0,B86-C86-H86)) -> 0 | J86: =J85+G86 -> 1973.6559
A87: 86 | B87: =MAX(0,I86) -> 0 | C87: =IF(B87<=0,0,IF(A87='Loan Calculator'!B12,MIN('Loan Calculator'!B11,B87),0)+IF(A87='Loan Calculator'!B14,MIN('Loan Calculator'!B13,B87),0)) -> 0 | D87: =IF(B87<=0,0,'Loan Calculator'!B4) -> 0 | E87: =IF(B87<=0,0,IF(A87>='Loan Calculator'!B18,'Loan Calculator'!B17,0)+IF(A87>='Loan Calculator'!B20,'Loan Calculator'!B19,0)+IF(A87>='Loan Calculator'!B22,'Loan Calculator'!B21,0)) -> 0 | F87: =IF(B87<=0,0,MIN(D87+E87,(B87-C87)*(1+'Loan Calculator'!B7))) -> 0 | G87: =IF(B87<=0,0,MAX(0,(B87-C87)*'Loan Calculator'!B7)) -> 0 | H87: =IF(B87<=0,0,F87-G87) -> 0 | I87: =IF(B87<=0,0,MAX(0,B87-C87-H87)) -> 0 | J87: =J86+G87 -> 1973.6559
A88: 87 | B88: =MAX(0,I87) -> 0 | C88: =IF(B88<=0,0,IF(A88='Loan Calculator'!B12,MIN('Loan Calculator'!B11,B88),0)+IF(A88='Loan Calculator'!B14,MIN('Loan Calculator'!B13,B88),0)) -> 0 | D88: =IF(B88<=0,0,'Loan Calculator'!B4) -> 0 | E88: =IF(B88<=0,0,IF(A88>='Loan Calculator'!B18,'Loan Calculator'!B17,0)+IF(A88>='Loan Calculator'!B20,'Loan Calculator'!B19,0)+IF(A88>='Loan Calculator'!B22,'Loan Calculator'!B21,0)) -> 0 | F88: =IF(B88<=0,0,MIN(D88+E88,(B88-C88)*(1+'Loan Calculator'!B7))) -> 0 | G88: =IF(B88<=0,0,MAX(0,(B88-C88)*'Loan Calculator'!B7)) -> 0 | H88: =IF(B88<=0,0,F88-G88) -> 0 | I88: =IF(B88<=0,0,MAX(0,B88-C88-H88)) -> 0 | J88: =J87+G88 -> 1973.6559
A89: 88 | B89: =MAX(0,I88) -> 0 | C89: =IF(B89<=0,0,IF(A89='Loan Calculator'!B12,MIN('Loan Calculator'!B11,B89),0)+IF(A89='Loan Calculator'!B14,MIN('Loan Calculator'!B13,B89),0)) -> 0 | D89: =IF(B89<=0,0,'Loan Calculator'!B4) -> 0 | E89: =IF(B89<=0,0,IF(A89>='Loan Calculator'!B18,'Loan Calculator'!B17,0)+IF(A89>='Loan Calculator'!B20,'Loan Calculator'!B19,0)+IF(A89>='Loan Calculator'!B22,'Loan Calculator'!B21,0)) -> 0 | F89: =IF(B89<=0,0,MIN(D89+E89,(B89-C89)*(1+'Loan Calculator'!B7))) -> 0 | G89: =IF(B89<=0,0,MAX(0,(B89-C89)*'Loan Calculator'!B7)) -> 0 | H89: =IF(B89<=0,0,F89-G89) -> 0 | I89: =IF(B89<=0,0,MAX(0,B89-C89-H89)) -> 0 | J89: =J88+G89 -> 1973.6559
A90: 89 | B90: =MAX(0,I89) -> 0 | C90: =IF(B90<=0,0,IF(A90='Loan Calculator'!B12,MIN('Loan Calculator'!B11,B90),0)+IF(A90='Loan Calculator'!B14,MIN('Loan Calculator'!B13,B90),0)) -> 0 | D90: =IF(B90<=0,0,'Loan Calculator'!B4) -> 0 | E90: =IF(B90<=0,0,IF(A90>='Loan Calculator'!B18,'Loan Calculator'!B17,0)+IF(A90>='Loan Calculator'!B20,'Loan Calculator'!B19,0)+IF(A90>='Loan Calculator'!B22,'Loan Calculator'!B21,0)) -> 0 | F90: =IF(B90<=0,0,MIN(D90+E90,(B90-C90)*(1+'Loan Calculator'!B7))) -> 0 | G90: =IF(B90<=0,0,MAX(0,(B90-C90)*'Loan Calculator'!B7)) -> 0 | H90: =IF(B90<=0,0,F90-G90) -> 0 | I90: =IF(B90<=0,0,MAX(0,B90-C90-H90)) -> 0 | J90: =J89+G90 -> 1973.6559
A91: 90 | B91: =MAX(0,I90) -> 0 | C91: =IF(B91<=0,0,IF(A91='Loan Calculator'!B12,MIN('Loan Calculator'!B11,B91),0)+IF(A91='Loan Calculator'!B14,MIN('Loan Calculator'!B13,B91),0)) -> 0 | D91: =IF(B91<=0,0,'Loan Calculator'!B4) -> 0 | E91: =IF(B91<=0,0,IF(A91>='Loan Calculator'!B18,'Loan Calculator'!B17,0)+IF(A91>='Loan Calculator'!B20,'Loan Calculator'!B19,0)+IF(A91>='Loan Calculator'!B22,'Loan Calculator'!B21,0)) -> 0 | F91: =IF(B91<=0,0,MIN(D91+E91,(B91-C91)*(1+'Loan Calculator'!B7))) -> 0 | G91: =IF(B91<=0,0,MAX(0,(B91-C91)*'Loan Calculator'!B7)) -> 0 | H91: =IF(B91<=0,0,F91-G91) -> 0 | I91: =IF(B91<=0,0,MAX(0,B91-C91-H91)) -> 0 | J91: =J90+G91 -> 1973.6559
A92: 91 | B92: =MAX(0,I91) -> 0 | C92: =IF(B92<=0,0,IF(A92='Loan Calculator'!B12,MIN('Loan Calculator'!B11,B92),0)+IF(A92='Loan Calculator'!B14,MIN('Loan Calculator'!B13,B92),0)) -> 0 | D92: =IF(B92<=0,0,'Loan Calculator'!B4) -> 0 | E92: =IF(B92<=0,0,IF(A92>='Loan Calculator'!B18,'Loan Calculator'!B17,0)+IF(A92>='Loan Calculator'!B20,'Loan Calculator'!B19,0)+IF(A92>='Loan Calculator'!B22,'Loan Calculator'!B21,0)) -> 0 | F92: =IF(B92<=0,0,MIN(D92+E92,(B92-C92)*(1+'Loan Calculator'!B7))) -> 0 | G92: =IF(B92<=0,0,MAX(0,(B92-C92)*'Loan Calculator'!B7)) -> 0 | H92: =IF(B92<=0,0,F92-G92) -> 0 | I92: =IF(B92<=0,0,MAX(0,B92-C92-H92)) -> 0 | J92: =J91+G92 -> 1973.6559
A93: 92 | B93: =MAX(0,I92) -> 0 | C93: =IF(B93<=0,0,IF(A93='Loan Calculator'!B12,MIN('Loan Calculator'!B11,B93),0)+IF(A93='Loan Calculator'!B14,MIN('Loan Calculator'!B13,B93),0)) -> 0 | D93: =IF(B93<=0,0,'Loan Calculator'!B4) -> 0 | E93: =IF(B93<=0,0,IF(A93>='Loan Calculator'!B18,'Loan Calculator'!B17,0)+IF(A93>='Loan Calculator'!B20,'Loan Calculator'!B19,0)+IF(A93>='Loan Calculator'!B22,'Loan Calculator'!B21,0)) -> 0 | F93: =IF(B93<=0,0,MIN(D93+E93,(B93-C93)*(1+'Loan Calculator'!B7))) -> 0 | G93: =IF(B93<=0,0,MAX(0,(B93-C93)*'Loan Calculator'!B7)) -> 0 | H93: =IF(B93<=0,0,F93-G93) -> 0 | I93: =IF(B93<=0,0,MAX(0,B93-C93-H93)) -> 0 | J93: =J92+G93 -> 1973.6559
A94: 93 | B94: =MAX(0,I93) -> 0 | C94: =IF(B94<=0,0,IF(A94='Loan Calculator'!B12,MIN('Loan Calculator'!B11,B94),0)+IF(A94='Loan Calculator'!B14,MIN('Loan Calculator'!B13,B94),0)) -> 0 | D94: =IF(B94<=0,0,'Loan Calculator'!B4) -> 0 | E94: =IF(B94<=0,0,IF(A94>='Loan Calculator'!B18,'Loan Calculator'!B17,0)+IF(A94>='Loan Calculator'!B20,'Loan Calculator'!B19,0)+IF(A94>='Loan Calculator'!B22,'Loan Calculator'!B21,0)) -> 0 | F94: =IF(B94<=0,0,MIN(D94+E94,(B94-C94)*(1+'Loan Calculator'!B7))) -> 0 | G94: =IF(B94<=0,0,MAX(0,(B94-C94)*'Loan Calculator'!B7)) -> 0 | H94: =IF(B94<=0,0,F94-G94) -> 0 | I94: =IF(B94<=0,0,MAX(0,B94-C94-H94)) -> 0 | J94: =J93+G94 -> 1973.6559
A95: 94 | B95: =MAX(0,I94) -> 0 | C95: =IF(B95<=0,0,IF(A95='Loan Calculator'!B12,MIN('Loan Calculator'!B11,B95),0)+IF(A95='Loan Calculator'!B14,MIN('Loan Calculator'!B13,B95),0)) -> 0 | D95: =IF(B95<=0,0,'Loan Calculator'!B4) -> 0 | E95: =IF(B95<=0,0,IF(A95>='Loan Calculator'!B18,'Loan Calculator'!B17,0)+IF(A95>='Loan Calculator'!B20,'Loan Calculator'!B19,0)+IF(A95>='Loan Calculator'!B22,'Loan Calculator'!B21,0)) -> 0 | F95: =IF(B95<=0,0,MIN(D95+E95,(B95-C95)*(1+'Loan Calculator'!B7))) -> 0 | G95: =IF(B95<=0,0,MAX(0,(B95-C95)*'Loan Calculator'!B7)) -> 0 | H95: =IF(B95<=0,0,F95-G95) -> 0 | I95: =IF(B95<=0,0,MAX(0,B95-C95-H95)) -> 0 | J95: =J94+G95 -> 1973.6559
A96: 95 | B96: =MAX(0,I95) -> 0 | C96: =IF(B96<=0,0,IF(A96='Loan Calculator'!B12,MIN('Loan Calculator'!B11,B96),0)+IF(A96='Loan Calculator'!B14,MIN('Loan Calculator'!B13,B96),0)) -> 0 | D96: =IF(B96<=0,0,'Loan Calculator'!B4) -> 0 | E96: =IF(B96<=0,0,IF(A96>='Loan Calculator'!B18,'Loan Calculator'!B17,0)+IF(A96>='Loan Calculator'!B20,'Loan Calculator'!B19,0)+IF(A96>='Loan Calculator'!B22,'Loan Calculator'!B21,0)) -> 0 | F96: =IF(B96<=0,0,MIN(D96+E96,(B96-C96)*(1+'Loan Calculator'!B7))) -> 0 | G96: =IF(B96<=0,0,MAX(0,(B96-C96)*'Loan Calculator'!B7)) -> 0 | H96: =IF(B96<=0,0,F96-G96) -> 0 | I96: =IF(B96<=0,0,MAX(0,B96-C96-H96)) -> 0 | J96: =J95+G96 -> 1973.6559
A97: 96 | B97: =MAX(0,I96) -> 0 | C97: =IF(B97<=0,0,IF(A97='Loan Calculator'!B12,MIN('Loan Calculator'!B11,B97),0)+IF(A97='Loan Calculator'!B14,MIN('Loan Calculator'!B13,B97),0)) -> 0 | D97: =IF(B97<=0,0,'Loan Calculator'!B4) -> 0 | E97: =IF(B97<=0,0,IF(A97>='Loan Calculator'!B18,'Loan Calculator'!B17,0)+IF(A97>='Loan Calculator'!B20,'Loan Calculator'!B19,0)+IF(A97>='Loan Calculator'!B22,'Loan Calculator'!B21,0)) -> 0 | F97: =IF(B97<=0,0,MIN(D97+E97,(B97-C97)*(1+'Loan Calculator'!B7))) -> 0 | G97: =IF(B97<=0,0,MAX(0,(B97-C97)*'Loan Calculator'!B7)) -> 0 | H97: =IF(B97<=0,0,F97-G97) -> 0 | I97: =IF(B97<=0,0,MAX(0,B97-C97-H97)) -> 0 | J97: =J96+G97 -> 1973.6559
A98: 97 | B98: =MAX(0,I97) -> 0 | C98: =IF(B98<=0,0,IF(A98='Loan Calculator'!B12,MIN('Loan Calculator'!B11,B98),0)+IF(A98='Loan Calculator'!B14,MIN('Loan Calculator'!B13,B98),0)) -> 0 | D98: =IF(B98<=0,0,'Loan Calculator'!B4) -> 0 | E98: =IF(B98<=0,0,IF(A98>='Loan Calculator'!B18,'Loan Calculator'!B17,0)+IF(A98>='Loan Calculator'!B20,'Loan Calculator'!B19,0)+IF(A98>='Loan Calculator'!B22,'Loan Calculator'!B21,0)) -> 0 | F98: =IF(B98<=0,0,MIN(D98+E98,(B98-C98)*(1+'Loan Calculator'!B7))) -> 0 | G98: =IF(B98<=0,0,MAX(0,(B98-C98)*'Loan Calculator'!B7)) -> 0 | H98: =IF(B98<=0,0,F98-G98) -> 0 | I98: =IF(B98<=0,0,MAX(0,B98-C98-H98)) -> 0 | J98: =J97+G98 -> 1973.6559
A99: 98 | B99: =MAX(0,I98) -> 0 | C99: =IF(B99<=0,0,IF(A99='Loan Calculator'!B12,MIN('Loan Calculator'!B11,B99),0)+IF(A99='Loan Calculator'!B14,MIN('Loan Calculator'!B13,B99),0)) -> 0 | D99: =IF(B99<=0,0,'Loan Calculator'!B4) -> 0 | E99: =IF(B99<=0,0,IF(A99>='Loan Calculator'!B18,'Loan Calculator'!B17,0)+IF(A99>='Loan Calculator'!B20,'Loan Calculator'!B19,0)+IF(A99>='Loan Calculator'!B22,'Loan Calculator'!B21,0)) -> 0 | F99: =IF(B99<=0,0,MIN(D99+E99,(B99-C99)*(1+'Loan Calculator'!B7))) -> 0 | G99: =IF(B99<=0,0,MAX(0,(B99-C99)*'Loan Calculator'!B7)) -> 0 | H99: =IF(B99<=0,0,F99-G99) -> 0 | I99: =IF(B99<=0,0,MAX(0,B99-C99-H99)) -> 0 | J99: =J98+G99 -> 1973.6559
A100: 99 | B100: =MAX(0,I99) -> 0 | C100: =IF(B100<=0,0,IF(A100='Loan Calculator'!B12,MIN('Loan Calculator'!B11,B100),0)+IF(A100='Loan Calculator'!B14,MIN('Loan Calculator'!B13,B100),0)) -> 0 | D100: =IF(B100<=0,0,'Loan Calculator'!B4) -> 0 | E100: =IF(B100<=0,0,IF(A100>='Loan Calculator'!B18,'Loan Calculator'!B17,0)+IF(A100>='Loan Calculator'!B20,'Loan Calculator'!B19,0)+IF(A100>='Loan Calculator'!B22,'Loan Calculator'!B21,0)) -> 0 | F100: =IF(B100<=0,0,MIN(D100+E100,(B100-C100)*(1+'Loan Calculator'!B7))) -> 0 | G100: =IF(B100<=0,0,MAX(0,(B100-C100)*'Loan Calculator'!B7)) -> 0 | H100: =IF(B100<=0,0,F100-G100) -> 0 | I100: =IF(B100<=0,0,MAX(0,B100-C100-H100)) -> 0 | J100: =J99+G100 -> 1973.6559
...

Sheet Baseline
A1: Period | B1: Opening Balance | C1: Payment | D1: Interest | E1: Principal | F1: Closing Balance | G1: Cumulative Interest
A2: 1 | B2: ='Loan Calculator'!B2 -> 36890 | C2: =IF(B2<=0,0,MIN('Loan Calculator'!B4,B2*(1+'Loan Calculator'!B7))) -> 365.72 | D2: =IF(B2<=0,0,B2*'Loan Calculator'!B7) -> 85.130769 | E2: =IF(B2<=0,0,C2-D2) -> 280.58923 | F2: =IF(B2<=0,0,MAX(0,B2-E2)) -> 36609.411 | G2: =D2 -> 85.130769 | I2: Total Periods: | J2: =COUNTIF(B2:B201,">"&0) -> 115
A3: 2 | B3: =MAX(0,F2) -> 36609.411 | C3: =IF(B3<=0,0,MIN('Loan Calculator'!B4,B3*(1+'Loan Calculator'!B7))) -> 365.72 | D3: =IF(B3<=0,0,B3*'Loan Calculator'!B7) -> 84.483256 | E3: =IF(B3<=0,0,C3-D3) -> 281.23674 | F3: =IF(B3<=0,0,MAX(0,B3-E3)) -> 36328.174 | G3: =G2+D3 -> 169.61402 | I3: Total Interest: | J3: =SUM(D2:D201) -> 5151.5318
A4: 3 | B4: =MAX(0,F3) -> 36328.174 | C4: =IF(B4<=0,0,MIN('Loan Calculator'!B4,B4*(1+'Loan Calculator'!B7))) -> 365.72 | D4: =IF(B4<=0,0,B4*'Loan Calculator'!B7) -> 83.834248 | E4: =IF(B4<=0,0,C4-D4) -> 281.88575 | F4: =IF(B4<=0,0,MAX(0,B4-E4)) -> 36046.288 | G4: =G3+D4 -> 253.44827 | I4: Total Payments: | J4: =SUM(C2:C201) -> 42041.532
A5: 4 | B5: =MAX(0,F4) -> 36046.288 | C5: =IF(B5<=0,0,MIN('Loan Calculator'!B4,B5*(1+'Loan Calculator'!B7))) -> 365.72 | D5: =IF(B5<=0,0,B5*'Loan Calculator'!B7) -> 83.183742 | E5: =IF(B5<=0,0,C5-D5) -> 282.53626 | F5: =IF(B5<=0,0,MAX(0,B5-E5)) -> 35763.752 | G5: =G4+D5 -> 336.63201
A6: 5 | B6: =MAX(0,F5) -> 35763.752 | C6: =IF(B6<=0,0,MIN('Loan Calculator'!B4,B6*(1+'Loan Calculator'!B7))) -> 365.72 | D6: =IF(B6<=0,0,B6*'Loan Calculator'!B7) -> 82.531735 | E6: =IF(B6<=0,0,C6-D6) -> 283.18826 | F6: =IF(B6<=0,0,MAX(0,B6-E6)) -> 35480.564 | G6: =G5+D6 -> 419.16375
A7: 6 | B7: =MAX(0,F6) -> 35480.564 | C7: =IF(B7<=0,0,MIN('Loan Calculator'!B4,B7*(1+'Loan Calculator'!B7))) -> 365.72 | D7: =IF(B7<=0,0,B7*'Loan Calculator'!B7) -> 81.878224 | E7: =IF(B7<=0,0,C7-D7) -> 283.84178 | F7: =IF(B7<=0,0,MAX(0,B7-E7)) -> 35196.722 | G7: =G6+D7 -> 501.04197
A8: 7 | B8: =MAX(0,F7) -> 35196.722 | C8: =IF(B8<=0,0,MIN('Loan Calculator'!B4,B8*(1+'Loan Calculator'!B7))) -> 365.72 | D8: =IF(B8<=0,0,B8*'Loan Calculator'!B7) -> 81.223205 | E8: =IF(B8<=0,0,C8-D8) -> 284.4968 | F8: =IF(B8<=0,0,MAX(0,B8-E8)) -> 34912.225 | G8: =G7+D8 -> 582.26518
A9: 8 | B9: =MAX(0,F8) -> 34912.225 | C9: =IF(B9<=0,0,MIN('Loan Calculator'!B4,B9*(1+'Loan Calculator'!B7))) -> 365.72 | D9: =IF(B9<=0,0,B9*'Loan Calculator'!B7) -> 80.566673 | E9: =IF(B9<=0,0,C9-D9) -> 285.15333 | F9: =IF(B9<=0,0,MAX(0,B9-E9)) -> 34627.072 | G9: =G8+D9 -> 662.83185
A10: 9 | B10: =MAX(0,F9) -> 34627.072 | C10: =IF(B10<=0,0,MIN('Loan Calculator'!B4,B10*(1+'Loan Calculator'!B7))) -> 365.72 | D10: =IF(B10<=0,0,B10*'Loan Calculator'!B7) -> 79.908627 | E10: =IF(B10<=0,0,C10-D10) -> 285.81137 | F10: =IF(B10<=0,0,MAX(0,B10-E10)) -> 34341.26 | G10: =G9+D10 -> 742.74048
A11: 10 | B11: =MAX(0,F10) -> 34341.26 | C11: =IF(B11<=0,0,MIN('Loan Calculator'!B4,B11*(1+'Loan Calculator'!B7))) -> 365.72 | D11: =IF(B11<=0,0,B11*'Loan Calculator'!B7) -> 79.249063 | E11: =IF(B11<=0,0,C11-D11) -> 286.47094 | F11: =IF(B11<=0,0,MAX(0,B11-E11)) -> 34054.79 | G11: =G10+D11 -> 821.98954
A12: 11 | B12: =MAX(0,F11) -> 34054.79 | C12: =IF(B12<=0,0,MIN('Loan Calculator'!B4,B12*(1+'Loan Calculator'!B7))) -> 365.72 | D12: =IF(B12<=0,0,B12*'Loan Calculator'!B7) -> 78.587976 | E12: =IF(B12<=0,0,C12-D12) -> 287.13202 | F12: =IF(B12<=0,0,MAX(0,B12-E12)) -> 33767.658 | G12: =G11+D12 -> 900.57752
A13: 12 | B13: =MAX(0,F12) -> 33767.658 | C13: =IF(B13<=0,0,MIN('Loan Calculator'!B4,B13*(1+'Loan Calculator'!B7))) -> 365.72 | D13: =IF(B13<=0,0,B13*'Loan Calculator'!B7) -> 77.925364 | E13: =IF(B13<=0,0,C13-D13) -> 287.79464 | F13: =IF(B13<=0,0,MAX(0,B13-E13)) -> 33479.863 | G13: =G12+D13 -> 978.50288
A14: 13 | B14: =MAX(0,F13) -> 33479.863 | C14: =IF(B14<=0,0,MIN('Loan Calculator'!B4,B14*(1+'Loan Calculator'!B7))) -> 365.72 | D14: =IF(B14<=0,0,B14*'Loan Calculator'!B7) -> 77.261222 | E14: =IF(B14<=0,0,C14-D14) -> 288.45878 | F14: =IF(B14<=0,0,MAX(0,B14-E14)) -> 33191.404 | G14: =G13+D14 -> 1055.7641
A15: 14 | B15: =MAX(0,F14) -> 33191.404 | C15: =IF(B15<=0,0,MIN('Loan Calculator'!B4,B15*(1+'Loan Calculator'!B7))) -> 365.72 | D15: =IF(B15<=0,0,B15*'Loan Calculator'!B7) -> 76.595548 | E15: =IF(B15<=0,0,C15-D15) -> 289.12445 | F15: =IF(B15<=0,0,MAX(0,B15-E15)) -> 32902.28 | G15: =G14+D15 -> 1132.3597
A16: 15 | B16: =MAX(0,F15) -> 32902.28 | C16: =IF(B16<=0,0,MIN('Loan Calculator'!B4,B16*(1+'Loan Calculator'!B7))) -> 365.72 | D16: =IF(B16<=0,0,B16*'Loan Calculator'!B7) -> 75.928338 | E16: =IF(B16<=0,0,C16-D16) -> 289.79166 | F16: =IF(B16<=0,0,MAX(0,B16-E16)) -> 32612.488 | G16: =G15+D16 -> 1208.288
A17: 16 | B17: =MAX(0,F16) -> 32612.488 | C17: =IF(B17<=0,0,MIN('Loan Calculator'!B4,B17*(1+'Loan Calculator'!B7))) -> 365.72 | D17: =IF(B17<=0,0,B17*'Loan Calculator'!B7) -> 75.259588 | E17: =IF(B17<=0,0,C17-D17) -> 290.46041 | F17: =IF(B17<=0,0,MAX(0,B17-E17)) -> 32322.028 | G17: =G16+D17 -> 1283.5476
A18: 17 | B18: =MAX(0,F17) -> 32322.028 | C18: =IF(B18<=0,0,MIN('Loan Calculator'!B4,B18*(1+'Loan Calculator'!B7))) -> 365.72 | D18: =IF(B18<=0,0,B18*'Loan Calculator'!B7) -> 74.589294 | E18: =IF(B18<=0,0,C18-D18) -> 291.13071 | F18: =IF(B18<=0,0,MAX(0,B18-E18)) -> 32030.897 | G18: =G17+D18 -> 1358.1369
A19: 18 | B19: =MAX(0,F18) -> 32030.897 | C19: =IF(B19<=0,0,MIN('Loan Calculator'!B4,B19*(1+'Loan Calculator'!B7))) -> 365.72 | D19: =IF(B19<=0,0,B19*'Loan Calculator'!B7) -> 73.917454 | E19: =IF(B19<=0,0,C19-D19) -> 291.80255 | F19: =IF(B19<=0,0,MAX(0,B19-E19)) -> 31739.094 | G19: =G18+D19 -> 1432.0543
A20: 19 | B20: =MAX(0,F19) -> 31739.094 | C20: =IF(B20<=0,0,MIN('Loan Calculator'!B4,B20*(1+'Loan Calculator'!B7))) -> 365.72 | D20: =IF(B20<=0,0,B20*'Loan Calculator'!B7) -> 73.244064 | E20: =IF(B20<=0,0,C20-D20) -> 292.47594 | F20: =IF(B20<=0,0,MAX(0,B20-E20)) -> 31446.618 | G20: =G19+D20 -> 1505.2984
A21: 20 | B21: =MAX(0,F20) -> 31446.618 | C21: =IF(B21<=0,0,MIN('Loan Calculator'!B4,B21*(1+'Loan Calculator'!B7))) -> 365.72 | D21: =IF(B21<=0,0,B21*'Loan Calculator'!B7) -> 72.569119 | E21: =IF(B21<=0,0,C21-D21) -> 293.15088 | F21: =IF(B21<=0,0,MAX(0,B21-E21)) -> 31153.468 | G21: =G20+D21 -> 1577.8675
A22: 21 | B22: =MAX(0,F21) -> 31153.468 | C22: =IF(B22<=0,0,MIN('Loan Calculator'!B4,B22*(1+'Loan Calculator'!B7))) -> 365.72 | D22: =IF(B22<=0,0,B22*'Loan Calculator'!B7) -> 71.892617 | E22: =IF(B22<=0,0,C22-D22) -> 293.82738 | F22: =IF(B22<=0,0,MAX(0,B22-E22)) -> 30859.64 | G22: =G21+D22 -> 1649.7601
A23: 22 | B23: =MAX(0,F22) -> 30859.64 | C23: =IF(B23<=0,0,MIN('Loan Calculator'!B4,B23*(1+'Loan Calculator'!B7))) -> 365.72 | D23: =IF(B23<=0,0,B23*'Loan Calculator'!B7) -> 71.214554 | E23: =IF(B23<=0,0,C23-D23) -> 294.50545 | F23: =IF(B23<=0,0,MAX(0,B23-E23)) -> 30565.135 | G23: =G22+D23 -> 1720.9747
A24: 23 | B24: =MAX(0,F23) -> 30565.135 | C24: =IF(B24<=0,0,MIN('Loan Calculator'!B4,B24*(1+'Loan Calculator'!B7))) -> 365.72 | D24: =IF(B24<=0,0,B24*'Loan Calculator'!B7) -> 70.534926 | E24: =IF(B24<=0,0,C24-D24) -> 295.18507 | F24: =IF(B24<=0,0,MAX(0,B24-E24)) -> 30269.95 | G24: =G23+D24 -> 1791.5096
A25: 24 | B25: =MAX(0,F24) -> 30269.95 | C25: =IF(B25<=0,0,MIN('Loan Calculator'!B4,B25*(1+'Loan Calculator'!B7))) -> 365.72 | D25: =IF(B25<=0,0,B25*'Loan Calculator'!B7) -> 69.85373 | E25: =IF(B25<=0,0,C25-D25) -> 295.86627 | F25: =IF(B25<=0,0,MAX(0,B25-E25)) -> 29974.083 | G25: =G24+D25 -> 1861.3633
A26: 25 | B26: =MAX(0,F25) -> 29974.083 | C26: =IF(B26<=0,0,MIN('Loan Calculator'!B4,B26*(1+'Loan Calculator'!B7))) -> 365.72 | D26: =IF(B26<=0,0,B26*'Loan Calculator'!B7) -> 69.170962 | E26: =IF(B26<=0,0,C26-D26) -> 296.54904 | F26: =IF(B26<=0,0,MAX(0,B26-E26)) -> 29677.534 | G26: =G25+D26 -> 1930.5343
A27: 26 | B27: =MAX(0,F26) -> 29677.534 | C27: =IF(B27<=0,0,MIN('Loan Calculator'!B4,B27*(1+'Loan Calculator'!B7))) -> 365.72 | D27: =IF(B27<=0,0,B27*'Loan Calculator'!B7) -> 68.486618 | E27: =IF(B27<=0,0,C27-D27) -> 297.23338 | F27: =IF(B27<=0,0,MAX(0,B27-E27)) -> 29380.301 | G27: =G26+D27 -> 1999.0209
A28: 27 | B28: =MAX(0,F27) -> 29380.301 | C28: =IF(B28<=0,0,MIN('Loan Calculator'!B4,B28*(1+'Loan Calculator'!B7))) -> 365.72 | D28: =IF(B28<=0,0,B28*'Loan Calculator'!B7) -> 67.800694 | E28: =IF(B28<=0,0,C28-D28) -> 297.91931 | F28: =IF(B28<=0,0,MAX(0,B28-E28)) -> 29082.382 | G28: =G27+D28 -> 2066.8216
A29: 28 | B29: =MAX(0,F28) -> 29082.382 | C29: =IF(B29<=0,0,MIN('Loan Calculator'!B4,B29*(1+'Loan Calculator'!B7))) -> 365.72 | D29: =IF(B29<=0,0,B29*'Loan Calculator'!B7) -> 67.113188 | E29: =IF(B29<=0,0,C29-D29) -> 298.60681 | F29: =IF(B29<=0,0,MAX(0,B29-E29)) -> 28783.775 | G29: =G28+D29 -> 2133.9348
A30: 29 | B30: =MAX(0,F29) -> 28783.775 | C30: =IF(B30<=0,0,MIN('Loan Calculator'!B4,B30*(1+'Loan Calculator'!B7))) -> 365.72 | D30: =IF(B30<=0,0,B30*'Loan Calculator'!B7) -> 66.424096 | E30: =IF(B30<=0,0,C30-D30) -> 299.2959 | F30: =IF(B30<=0,0,MAX(0,B30-E30)) -> 28484.479 | G30: =G29+D30 -> 2200.3589
A31: 30 | B31: =MAX(0,F30) -> 28484.479 | C31: =IF(B31<=0,0,MIN('Loan Calculator'!B4,B31*(1+'Loan Calculator'!B7))) -> 365.72 | D31: =IF(B31<=0,0,B31*'Loan Calculator'!B7) -> 65.733413 | E31: =IF(B31<=0,0,C31-D31) -> 299.98659 | F31: =IF(B31<=0,0,MAX(0,B31-E31)) -> 28184.492 | G31: =G30+D31 -> 2266.0923
A32: 31 | B32: =MAX(0,F31) -> 28184.492 | C32: =IF(B32<=0,0,MIN('Loan Calculator'!B4,B32*(1+'Loan Calculator'!B7))) -> 365.72 | D32: =IF(B32<=0,0,B32*'Loan Calculator'!B7) -> 65.041136 | E32: =IF(B32<=0,0,C32-D32) -> 300.67886 | F32: =IF(B32<=0,0,MAX(0,B32-E32)) -> 27883.813 | G32: =G31+D32 -> 2331.1334
A33: 32 | B33: =MAX(0,F32) -> 27883.813 | C33: =IF(B33<=0,0,MIN('Loan Calculator'!B4,B33*(1+'Loan Calculator'!B7))) -> 365.72 | D33: =IF(B33<=0,0,B33*'Loan Calculator'!B7) -> 64.347262 | E33: =IF(B33<=0,0,C33-D33) -> 301.37274 | F33: =IF(B33<=0,0,MAX(0,B33-E33)) -> 27582.441 | G33: =G32+D33 -> 2395.4807
A34: 33 | B34: =MAX(0,F33) -> 27582.441 | C34: =IF(B34<=0,0,MIN('Loan Calculator'!B4,B34*(1+'Loan Calculator'!B7))) -> 365.72 | D34: =IF(B34<=0,0,B34*'Loan Calculator'!B7) -> 63.651786 | E34: =IF(B34<=0,0,C34-D34) -> 302.06821 | F34: =IF(B34<=0,0,MAX(0,B34-E34)) -> 27280.372 | G34: =G33+D34 -> 2459.1325
A35: 34 | B35: =MAX(0,F34) -> 27280.372 | C35: =IF(B35<=0,0,MIN('Loan Calculator'!B4,B35*(1+'Loan Calculator'!B7))) -> 365.72 | D35: =IF(B35<=0,0,B35*'Loan Calculator'!B7) -> 62.954706 | E35: =IF(B35<=0,0,C35-D35) -> 302.76529 | F35: =IF(B35<=0,0,MAX(0,B35-E35)) -> 26977.607 | G35: =G34+D35 -> 2522.0872
A36: 35 | B36: =MAX(0,F35) -> 26977.607 | C36: =IF(B36<=0,0,MIN('Loan Calculator'!B4,B36*(1+'Loan Calculator'!B7))) -> 365.72 | D36: =IF(B36<=0,0,B36*'Loan Calculator'!B7) -> 62.256017 | E36: =IF(B36<=0,0,C36-D36) -> 303.46398 | F36: =IF(B36<=0,0,MAX(0,B36-E36)) -> 26674.143 | G36: =G35+D36 -> 2584.3432
A37: 36 | B37: =MAX(0,F36) -> 26674.143 | C37: =IF(B37<=0,0,MIN('Loan Calculator'!B4,B37*(1+'Loan Calculator'!B7))) -> 365.72 | D37: =IF(B37<=0,0,B37*'Loan Calculator'!B7) -> 61.555715 | E37: =IF(B37<=0,0,C37-D37) -> 304.16428 | F37: =IF(B37<=0,0,MAX(0,B37-E37)) -> 26369.979 | G37: =G36+D37 -> 2645.8989
A38: 37 | B38: =MAX(0,F37) -> 26369.979 | C38: =IF(B38<=0,0,MIN('Loan Calculator'!B4,B38*(1+'Loan Calculator'!B7))) -> 365.72 | D38: =IF(B38<=0,0,B38*'Loan Calculator'!B7) -> 60.853798 | E38: =IF(B38<=0,0,C38-D38) -> 304.8662 | F38: =IF(B38<=0,0,MAX(0,B38-E38)) -> 26065.113 | G38: =G37+D38 -> 2706.7527
A39: 38 | B39: =MAX(0,F38) -> 26065.113 | C39: =IF(B39<=0,0,MIN('Loan Calculator'!B4,B39*(1+'Loan Calculator'!B7))) -> 365.72 | D39: =IF(B39<=0,0,B39*'Loan Calculator'!B7) -> 60.15026 | E39: =IF(B39<=0,0,C39-D39) -> 305.56974 | F39: =IF(B39<=0,0,MAX(0,B39-E39)) -> 25759.543 | G39: =G38+D39 -> 2766.903
A40: 39 | B40: =MAX(0,F39) -> 25759.543 | C40: =IF(B40<=0,0,MIN('Loan Calculator'!B4,B40*(1+'Loan Calculator'!B7))) -> 365.72 | D40: =IF(B40<=0,0,B40*'Loan Calculator'!B7) -> 59.445099 | E40: =IF(B40<=0,0,C40-D40) -> 306.2749 | F40: =IF(B40<=0,0,MAX(0,B40-E40)) -> 25453.268 | G40: =G39+D40 -> 2826.3481
A41: 40 | B41: =MAX(0,F40) -> 25453.268 | C41: =IF(B41<=0,0,MIN('Loan Calculator'!B4,B41*(1+'Loan Calculator'!B7))) -> 365.72 | D41: =IF(B41<=0,0,B41*'Loan Calculator'!B7) -> 58.738311 | E41: =IF(B41<=0,0,C41-D41) -> 306.98169 | F41: =IF(B41<=0,0,MAX(0,B41-E41)) -> 25146.286 | G41: =G40+D41 -> 2885.0864
A42: 41 | B42: =MAX(0,F41) -> 25146.286 | C42: =IF(B42<=0,0,MIN('Loan Calculator'!B4,B42*(1+'Loan Calculator'!B7))) -> 365.72 | D42: =IF(B42<=0,0,B42*'Loan Calculator'!B7) -> 58.029892 | E42: =IF(B42<=0,0,C42-D42) -> 307.69011 | F42: =IF(B42<=0,0,MAX(0,B42-E42)) -> 24838.596 | G42: =G41+D42 -> 2943.1163
A43: 42 | B43: =MAX(0,F42) -> 24838.596 | C43: =IF(B43<=0,0,MIN('Loan Calculator'!B4,B43*(1+'Loan Calculator'!B7))) -> 365.72 | D43: =IF(B43<=0,0,B43*'Loan Calculator'!B7) -> 57.319838 | E43: =IF(B43<=0,0,C43-D43) -> 308.40016 | F43: =IF(B43<=0,0,MAX(0,B43-E43)) -> 24530.196 | G43: =G42+D43 -> 3000.4361
A44: 43 | B44: =MAX(0,F43) -> 24530.196 | C44: =IF(B44<=0,0,MIN('Loan Calculator'!B4,B44*(1+'Loan Calculator'!B7))) -> 365.72 | D44: =IF(B44<=0,0,B44*'Loan Calculator'!B7) -> 56.608145 | E44: =IF(B44<=0,0,C44-D44) -> 309.11186 | F44: =IF(B44<=0,0,MAX(0,B44-E44)) -> 24221.084 | G44: =G43+D44 -> 3057.0443
A45: 44 | B45: =MAX(0,F44) -> 24221.084 | C45: =IF(B45<=0,0,MIN('Loan Calculator'!B4,B45*(1+'Loan Calculator'!B7))) -> 365.72 | D45: =IF(B45<=0,0,B45*'Loan Calculator'!B7) -> 55.89481 | E45: =IF(B45<=0,0,C45-D45) -> 309.82519 | F45: =IF(B45<=0,0,MAX(0,B45-E45)) -> 23911.259 | G45: =G44+D45 -> 3112.9391
A46: 45 | B46: =MAX(0,F45) -> 23911.259 | C46: =IF(B46<=0,0,MIN('Loan Calculator'!B4,B46*(1+'Loan Calculator'!B7))) -> 365.72 | D46: =IF(B46<=0,0,B46*'Loan Calculator'!B7) -> 55.179829 | E46: =IF(B46<=0,0,C46-D46) -> 310.54017 | F46: =IF(B46<=0,0,MAX(0,B46-E46)) -> 23600.719 | G46: =G45+D46 -> 3168.1189
A47: 46 | B47: =MAX(0,F46) -> 23600.719 | C47: =IF(B47<=0,0,MIN('Loan Calculator'!B4,B47*(1+'Loan Calculator'!B7))) -> 365.72 | D47: =IF(B47<=0,0,B47*'Loan Calculator'!B7) -> 54.463197 | E47: =IF(B47<=0,0,C47-D47) -> 311.2568 | F47: =IF(B47<=0,0,MAX(0,B47-E47)) -> 23289.462 | G47: =G46+D47 -> 3222.5821
A48: 47 | B48: =MAX(0,F47) -> 23289.462 | C48: =IF(B48<=0,0,MIN('Loan Calculator'!B4,B48*(1+'Loan Calculator'!B7))) -> 365.72 | D48: =IF(B48<=0,0,B48*'Loan Calculator'!B7) -> 53.744913 | E48: =IF(B48<=0,0,C48-D48) -> 311.97509 | F48: =IF(B48<=0,0,MAX(0,B48-E48)) -> 22977.487 | G48: =G47+D48 -> 3276.327
A49: 48 | B49: =MAX(0,F48) -> 22977.487 | C49: =IF(B49<=0,0,MIN('Loan Calculator'!B4,B49*(1+'Loan Calculator'!B7))) -> 365.72 | D49: =IF(B49<=0,0,B49*'Loan Calculator'!B7) -> 53.02497 | E49: =IF(B49<=0,0,C49-D49) -> 312.69503 | F49: =IF(B49<=0,0,MAX(0,B49-E49)) -> 22664.792 | G49: =G48+D49 -> 3329.352
A50: 49 | B50: =MAX(0,F49) -> 22664.792 | C50: =IF(B50<=0,0,MIN('Loan Calculator'!B4,B50*(1+'Loan Calculator'!B7))) -> 365.72 | D50: =IF(B50<=0,0,B50*'Loan Calculator'!B7) -> 52.303366 | E50: =IF(B50<=0,0,C50-D50) -> 313.41663 | F50: =IF(B50<=0,0,MAX(0,B50-E50)) -> 22351.375 | G50: =G49+D50 -> 3381.6554
A51: 50 | B51: =MAX(0,F50) -> 22351.375 | C51: =IF(B51<=0,0,MIN('Loan Calculator'!B4,B51*(1+'Loan Calculator'!B7))) -> 365.72 | D51: =IF(B51<=0,0,B51*'Loan Calculator'!B7) -> 51.580097 | E51: =IF(B51<=0,0,C51-D51) -> 314.1399 | F51: =IF(B51<=0,0,MAX(0,B51-E51)) -> 22037.235 | G51: =G50+D51 -> 3433.2355
A52: 51 | B52: =MAX(0,F51) -> 22037.235 | C52: =IF(B52<=0,0,MIN('Loan Calculator'!B4,B52*(1+'Loan Calculator'!B7))) -> 365.72 | D52: =IF(B52<=0,0,B52*'Loan Calculator'!B7) -> 50.855159 | E52: =IF(B52<=0,0,C52-D52) -> 314.86484 | F52: =IF(B52<=0,0,MAX(0,B52-E52)) -> 21722.371 | G52: =G51+D52 -> 3484.0906
A53: 52 | B53: =MAX(0,F52) -> 21722.371 | C53: =IF(B53<=0,0,MIN('Loan Calculator'!B4,B53*(1+'Loan Calculator'!B7))) -> 365.72 | D53: =IF(B53<=0,0,B53*'Loan Calculator'!B7) -> 50.128548 | E53: =IF(B53<=0,0,C53-D53) -> 315.59145 | F53: =IF(B53<=0,0,MAX(0,B53-E53)) -> 21406.779 | G53: =G52+D53 -> 3534.2192
A54: 53 | B54: =MAX(0,F53) -> 21406.779 | C54: =IF(B54<=0,0,MIN('Loan Calculator'!B4,B54*(1+'Loan Calculator'!B7))) -> 365.72 | D54: =IF(B54<=0,0,B54*'Loan Calculator'!B7) -> 49.40026 | E54: =IF(B54<=0,0,C54-D54) -> 316.31974 | F54: =IF(B54<=0,0,MAX(0,B54-E54)) -> 21090.459 | G54: =G53+D54 -> 3583.6194
A55: 54 | B55: =MAX(0,F54) -> 21090.459 | C55: =IF(B55<=0,0,MIN('Loan Calculator'!B4,B55*(1+'Loan Calculator'!B7))) -> 365.72 | D55: =IF(B55<=0,0,B55*'Loan Calculator'!B7) -> 48.670291 | E55: =IF(B55<=0,0,C55-D55) -> 317.04971 | F55: =IF(B55<=0,0,MAX(0,B55-E55)) -> 20773.41 | G55: =G54+D55 -> 3632.2897
A56: 55 | B56: =MAX(0,F55) -> 20773.41 | C56: =IF(B56<=0,0,MIN('Loan Calculator'!B4,B56*(1+'Loan Calculator'!B7))) -> 365.72 | D56: =IF(B56<=0,0,B56*'Loan Calculator'!B7) -> 47.938638 | E56: =IF(B56<=0,0,C56-D56) -> 317.78136 | F56: =IF(B56<=0,0,MAX(0,B56-E56)) -> 20455.628 | G56: =G55+D56 -> 3680.2283
A57: 56 | B57: =MAX(0,F56) -> 20455.628 | C57: =IF(B57<=0,0,MIN('Loan Calculator'!B4,B57*(1+'Loan Calculator'!B7))) -> 365.72 | D57: =IF(B57<=0,0,B57*'Loan Calculator'!B7) -> 47.205296 | E57: =IF(B57<=0,0,C57-D57) -> 318.5147 | F57: =IF(B57<=0,0,MAX(0,B57-E57)) -> 20137.114 | G57: =G56+D57 -> 3727.4336
A58: 57 | B58: =MAX(0,F57) -> 20137.114 | C58: =IF(B58<=0,0,MIN('Loan Calculator'!B4,B58*(1+'Loan Calculator'!B7))) -> 365.72 | D58: =IF(B58<=0,0,B58*'Loan Calculator'!B7) -> 46.470262 | E58: =IF(B58<=0,0,C58-D58) -> 319.24974 | F58: =IF(B58<=0,0,MAX(0,B58-E58)) -> 19817.864 | G58: =G57+D58 -> 3773.9039
A59: 58 | B59: =MAX(0,F58) -> 19817.864 | C59: =IF(B59<=0,0,MIN('Loan Calculator'!B4,B59*(1+'Loan Calculator'!B7))) -> 365.72 | D59: =IF(B59<=0,0,B59*'Loan Calculator'!B7) -> 45.733532 | E59: =IF(B59<=0,0,C59-D59) -> 319.98647 | F59: =IF(B59<=0,0,MAX(0,B59-E59)) -> 19497.877 | G59: =G58+D59 -> 3819.6374
A60: 59 | B60: =MAX(0,F59) -> 19497.877 | C60: =IF(B60<=0,0,MIN('Loan Calculator'!B4,B60*(1+'Loan Calculator'!B7))) -> 365.72 | D60: =IF(B60<=0,0,B60*'Loan Calculator'!B7) -> 44.995102 | E60: =IF(B60<=0,0,C60-D60) -> 320.7249 | F60: =IF(B60<=0,0,MAX(0,B60-E60)) -> 19177.153 | G60: =G59+D60 -> 3864.6325
A61: 60 | B61: =MAX(0,F60) -> 19177.153 | C61: =IF(B61<=0,0,MIN('Loan Calculator'!B4,B61*(1+'Loan Calculator'!B7))) -> 365.72 | D61: =IF(B61<=0,0,B61*'Loan Calculator'!B7) -> 44.254967 | E61: =IF(B61<=0,0,C61-D61) -> 321.46503 | F61: =IF(B61<=0,0,MAX(0,B61-E61)) -> 18855.688 | G61: =G60+D61 -> 3908.8875
A62: 61 | B62: =MAX(0,F61) -> 18855.688 | C62: =IF(B62<=0,0,MIN('Loan Calculator'!B4,B62*(1+'Loan Calculator'!B7))) -> 365.72 | D62: =IF(B62<=0,0,B62*'Loan Calculator'!B7) -> 43.513125 | E62: =IF(B62<=0,0,C62-D62) -> 322.20687 | F62: =IF(B62<=0,0,MAX(0,B62-E62)) -> 18533.481 | G62: =G61+D62 -> 3952.4006
A63: 62 | B63: =MAX(0,F62) -> 18533.481 | C63: =IF(B63<=0,0,MIN('Loan Calculator'!B4,B63*(1+'Loan Calculator'!B7))) -> 365.72 | D63: =IF(B63<=0,0,B63*'Loan Calculator'!B7) -> 42.769571 | E63: =IF(B63<=0,0,C63-D63) -> 322.95043 | F63: =IF(B63<=0,0,MAX(0,B63-E63)) -> 18210.53 | G63: =G62+D63 -> 3995.1702
A64: 63 | B64: =MAX(0,F63) -> 18210.53 | C64: =IF(B64<=0,0,MIN('Loan Calculator'!B4,B64*(1+'Loan Calculator'!B7))) -> 365.72 | D64: =IF(B64<=0,0,B64*'Loan Calculator'!B7) -> 42.0243 | E64: =IF(B64<=0,0,C64-D64) -> 323.6957 | F64: =IF(B64<=0,0,MAX(0,B64-E64)) -> 17886.835 | G64: =G63+D64 -> 4037.1945
A65: 64 | B65: =MAX(0,F64) -> 17886.835 | C65: =IF(B65<=0,0,MIN('Loan Calculator'!B4,B65*(1+'Loan Calculator'!B7))) -> 365.72 | D65: =IF(B65<=0,0,B65*'Loan Calculator'!B7) -> 41.27731 | E65: =IF(B65<=0,0,C65-D65) -> 324.44269 | F65: =IF(B65<=0,0,MAX(0,B65-E65)) -> 17562.392 | G65: =G64+D65 -> 4078.4718
A66: 65 | B66: =MAX(0,F65) -> 17562.392 | C66: =IF(B66<=0,0,MIN('Loan Calculator'!B4,B66*(1+'Loan Calculator'!B7))) -> 365.72 | D66: =IF(B66<=0,0,B66*'Loan Calculator'!B7) -> 40.528596 | E66: =IF(B66<=0,0,C66-D66) -> 325.1914 | F66: =IF(B66<=0,0,MAX(0,B66-E66)) -> 17237.2 | G66: =G65+D66 -> 4119.0004
A67: 66 | B67: =MAX(0,F66) -> 17237.2 | C67: =IF(B67<=0,0,MIN('Loan Calculator'!B4,B67*(1+'Loan Calculator'!B7))) -> 365.72 | D67: =IF(B67<=0,0,B67*'Loan Calculator'!B7) -> 39.778155 | E67: =IF(B67<=0,0,C67-D67) -> 325.94185 | F67: =IF(B67<=0,0,MAX(0,B67-E67)) -> 16911.259 | G67: =G66+D67 -> 4158.7786
A68: 67 | B68: =MAX(0,F67) -> 16911.259 | C68: =IF(B68<=0,0,MIN('Loan Calculator'!B4,B68*(1+'Loan Calculator'!B7))) -> 365.72 | D68: =IF(B68<=0,0,B68*'Loan Calculator'!B7) -> 39.025981 | E68: =IF(B68<=0,0,C68-D68) -> 326.69402 | F68: =IF(B68<=0,0,MAX(0,B68-E68)) -> 16584.565 | G68: =G67+D68 -> 4197.8045
A69: 68 | B69: =MAX(0,F68) -> 16584.565 | C69: =IF(B69<=0,0,MIN('Loan Calculator'!B4,B69*(1+'Loan Calculator'!B7))) -> 365.72 | D69: =IF(B69<=0,0,B69*'Loan Calculator'!B7) -> 38.272072 | E69: =IF(B69<=0,0,C69-D69) -> 327.44793 | F69: =IF(B69<=0,0,MAX(0,B69-E69)) -> 16257.117 | G69: =G68+D69 -> 4236.0766
A70: 69 | B70: =MAX(0,F69) -> 16257.117 | C70: =IF(B70<=0,0,MIN('Loan Calculator'!B4,B70*(1+'Loan Calculator'!B7))) -> 365.72 | D70: =IF(B70<=0,0,B70*'Loan Calculator'!B7) -> 37.516423 | E70: =IF(B70<=0,0,C70-D70) -> 328.20358 | F70: =IF(B70<=0,0,MAX(0,B70-E70)) -> 15928.913 | G70: =G69+D70 -> 4273.593
A71: 70 | B71: =MAX(0,F70) -> 15928.913 | C71: =IF(B71<=0,0,MIN('Loan Calculator'!B4,B71*(1+'Loan Calculator'!B7))) -> 365.72 | D71: =IF(B71<=0,0,B71*'Loan Calculator'!B7) -> 36.75903 | E71: =IF(B71<=0,0,C71-D71) -> 328.96097 | F71: =IF(B71<=0,0,MAX(0,B71-E71)) -> 15599.952 | G71: =G70+D71 -> 4310.3521
A72: 71 | B72: =MAX(0,F71) -> 15599.952 | C72: =IF(B72<=0,0,MIN('Loan Calculator'!B4,B72*(1+'Loan Calculator'!B7))) -> 365.72 | D72: =IF(B72<=0,0,B72*'Loan Calculator'!B7) -> 35.999889 | E72: =IF(B72<=0,0,C72-D72) -> 329.72011 | F72: =IF(B72<=0,0,MAX(0,B72-E72)) -> 15270.232 | G72: =G71+D72 -> 4346.352
A73: 72 | B73: =MAX(0,F72) -> 15270.232 | C73: =IF(B73<=0,0,MIN('Loan Calculator'!B4,B73*(1+'Loan Calculator'!B7))) -> 365.72 | D73: =IF(B73<=0,0,B73*'Loan Calculator'!B7) -> 35.238997 | E73: =IF(B73<=0,0,C73-D73) -> 330.481 | F73: =IF(B73<=0,0,MAX(0,B73-E73)) -> 14939.751 | G73: =G72+D73 -> 4381.591
A74: 73 | B74: =MAX(0,F73) -> 14939.751 | C74: =IF(B74<=0,0,MIN('Loan Calculator'!B4,B74*(1+'Loan Calculator'!B7))) -> 365.72 | D74: =IF(B74<=0,0,B74*'Loan Calculator'!B7) -> 34.476348 | E74: =IF(B74<=0,0,C74-D74) -> 331.24365 | F74: =IF(B74<=0,0,MAX(0,B74-E74)) -> 14608.507 | G74: =G73+D74 -> 4416.0673
A75: 74 | B75: =MAX(0,F74) -> 14608.507 | C75: =IF(B75<=0,0,MIN('Loan Calculator'!B4,B75*(1+'Loan Calculator'!B7))) -> 365.72 | D75: =IF(B75<=0,0,B75*'Loan Calculator'!B7) -> 33.71194 | E75: =IF(B75<=0,0,C75-D75) -> 332.00806 | F75: =IF(B75<=0,0,MAX(0,B75-E75)) -> 14276.499 | G75: =G74+D75 -> 4449.7792
A76: 75 | B76: =MAX(0,F75) -> 14276.499 | C76: =IF(B76<=0,0,MIN('Loan Calculator'!B4,B76*(1+'Loan Calculator'!B7))) -> 365.72 | D76: =IF(B76<=0,0,B76*'Loan Calculator'!B7) -> 32.945767 | E76: =IF(B76<=0,0,C76-D76) -> 332.77423 | F76: =IF(B76<=0,0,MAX(0,B76-E76)) -> 13943.725 | G76: =G75+D76 -> 4482.725
A77: 76 | B77: =MAX(0,F76) -> 13943.725 | C77: =IF(B77<=0,0,MIN('Loan Calculator'!B4,B77*(1+'Loan Calculator'!B7))) -> 365.72 | D77: =IF(B77<=0,0,B77*'Loan Calculator'!B7) -> 32.177827 | E77: =IF(B77<=0,0,C77-D77) -> 333.54217 | F77: =IF(B77<=0,0,MAX(0,B77-E77)) -> 13610.183 | G77: =G76+D77 -> 4514.9028
A78: 77 | B78: =MAX(0,F77) -> 13610.183 | C78: =IF(B78<=0,0,MIN('Loan Calculator'!B4,B78*(1+'Loan Calculator'!B7))) -> 365.72 | D78: =IF(B78<=0,0,B78*'Loan Calculator'!B7) -> 31.408114 | E78: =IF(B78<=0,0,C78-D78) -> 334.31189 | F78: =IF(B78<=0,0,MAX(0,B78-E78)) -> 13275.871 | G78: =G77+D78 -> 4546.311
A79: 78 | B79: =MAX(0,F78) -> 13275.871 | C79: =IF(B79<=0,0,MIN('Loan Calculator'!B4,B79*(1+'Loan Calculator'!B7))) -> 365.72 | D79: =IF(B79<=0,0,B79*'Loan Calculator'!B7) -> 30.636625 | E79: =IF(B79<=0,0,C79-D79) -> 335.08337 | F79: =IF(B79<=0,0,MAX(0,B79-E79)) -> 12940.788 | G79: =G78+D79 -> 4576.9476
A80: 79 | B80: =MAX(0,F79) -> 12940.788 | C80: =IF(B80<=0,0,MIN('Loan Calculator'!B4,B80*(1+'Loan Calculator'!B7))) -> 365.72 | D80: =IF(B80<=0,0,B80*'Loan Calculator'!B7) -> 29.863356 | E80: =IF(B80<=0,0,C80-D80) -> 335.85664 | F80: =IF(B80<=0,0,MAX(0,B80-E80)) -> 12604.931 | G80: =G79+D80 -> 4606.8109
A81: 80 | B81: =MAX(0,F80) -> 12604.931 | C81: =IF(B81<=0,0,MIN('Loan Calculator'!B4,B81*(1+'Loan Calculator'!B7))) -> 365.72 | D81: =IF(B81<=0,0,B81*'Loan Calculator'!B7) -> 29.088302 | E81: =IF(B81<=0,0,C81-D81) -> 336.6317 | F81: =IF(B81<=0,0,MAX(0,B81-E81)) -> 12268.299 | G81: =G80+D81 -> 4635.8992
A82: 81 | B82: =MAX(0,F81) -> 12268.299 | C82: =IF(B82<=0,0,MIN('Loan Calculator'!B4,B82*(1+'Loan Calculator'!B7))) -> 365.72 | D82: =IF(B82<=0,0,B82*'Loan Calculator'!B7) -> 28.31146 | E82: =IF(B82<=0,0,C82-D82) -> 337.40854 | F82: =IF(B82<=0,0,MAX(0,B82-E82)) -> 11930.891 | G82: =G81+D82 -> 4664.2107
A83: 82 | B83: =MAX(0,F82) -> 11930.891 | C83: =IF(B83<=0,0,MIN('Loan Calculator'!B4,B83*(1+'Loan Calculator'!B7))) -> 365.72 | D83: =IF(B83<=0,0,B83*'Loan Calculator'!B7) -> 27.532825 | E83: =IF(B83<=0,0,C83-D83) -> 338.18718 | F83: =IF(B83<=0,0,MAX(0,B83-E83)) -> 11592.704 | G83: =G82+D83 -> 4691.7435
A84: 83 | B84: =MAX(0,F83) -> 11592.704 | C84: =IF(B84<=0,0,MIN('Loan Calculator'!B4,B84*(1+'Loan Calculator'!B7))) -> 365.72 | D84: =IF(B84<=0,0,B84*'Loan Calculator'!B7) -> 26.752393 | E84: =IF(B84<=0,0,C84-D84) -> 338.96761 | F84: =IF(B84<=0,0,MAX(0,B84-E84)) -> 11253.736 | G84: =G83+D84 -> 4718.4959
A85: 84 | B85: =MAX(0,F84) -> 11253.736 | C85: =IF(B85<=0,0,MIN('Loan Calculator'!B4,B85*(1+'Loan Calculator'!B7))) -> 365.72 | D85: =IF(B85<=0,0,B85*'Loan Calculator'!B7) -> 25.97016 | E85: =IF(B85<=0,0,C85-D85) -> 339.74984 | F85: =IF(B85<=0,0,MAX(0,B85-E85)) -> 10913.986 | G85: =G84+D85 -> 4744.4661
A86: 85 | B86: =MAX(0,F85) -> 10913.986 | C86: =IF(B86<=0,0,MIN('Loan Calculator'!B4,B86*(1+'Loan Calculator'!B7))) -> 365.72 | D86: =IF(B86<=0,0,B86*'Loan Calculator'!B7) -> 25.186122 | E86: =IF(B86<=0,0,C86-D86) -> 340.53388 | F86: =IF(B86<=0,0,MAX(0,B86-E86)) -> 10573.452 | G86: =G85+D86 -> 4769.6522
A87: 86 | B87: =MAX(0,F86) -> 10573.452 | C87: =IF(B87<=0,0,MIN('Loan Calculator'!B4,B87*(1+'Loan Calculator'!B7))) -> 365.72 | D87: =IF(B87<=0,0,B87*'Loan Calculator'!B7) -> 24.400274 | E87: =IF(B87<=0,0,C87-D87) -> 341.31973 | F87: =IF(B87<=0,0,MAX(0,B87-E87)) -> 10232.132 | G87: =G86+D87 -> 4794.0525
A88: 87 | B88: =MAX(0,F87) -> 10232.132 | C88: =IF(B88<=0,0,MIN('Loan Calculator'!B4,B88*(1+'Loan Calculator'!B7))) -> 365.72 | D88: =IF(B88<=0,0,B88*'Loan Calculator'!B7) -> 23.612613 | E88: =IF(B88<=0,0,C88-D88) -> 342.10739 | F88: =IF(B88<=0,0,MAX(0,B88-E88)) -> 9890.0251 | G88: =G87+D88 -> 4817.6651
A89: 88 | B89: =MAX(0,F88) -> 9890.0251 | C89: =IF(B89<=0,0,MIN('Loan Calculator'!B4,B89*(1+'Loan Calculator'!B7))) -> 365.72 | D89: =IF(B89<=0,0,B89*'Loan Calculator'!B7) -> 22.823135 | E89: =IF(B89<=0,0,C89-D89) -> 342.89687 | F89: =IF(B89<=0,0,MAX(0,B89-E89)) -> 9547.1282 | G89: =G88+D89 -> 4840.4882
A90: 89 | B90: =MAX(0,F89) -> 9547.1282 | C90: =IF(B90<=0,0,MIN('Loan Calculator'!B4,B90*(1+'Loan Calculator'!B7))) -> 365.72 | D90: =IF(B90<=0,0,B90*'Loan Calculator'!B7) -> 22.031834 | E90: =IF(B90<=0,0,C90-D90) -> 343.68817 | F90: =IF(B90<=0,0,MAX(0,B90-E90)) -> 9203.4401 | G90: =G89+D90 -> 4862.5201
A91: 90 | B91: =MAX(0,F90) -> 9203.4401 | C91: =IF(B91<=0,0,MIN('Loan Calculator'!B4,B91*(1+'Loan Calculator'!B7))) -> 365.72 | D91: =IF(B91<=0,0,B91*'Loan Calculator'!B7) -> 21.238708 | E91: =IF(B91<=0,0,C91-D91) -> 344.48129 | F91: =IF(B91<=0,0,MAX(0,B91-E91)) -> 8858.9588 | G91: =G90+D91 -> 4883.7588
A92: 91 | B92: =MAX(0,F91) -> 8858.9588 | C92: =IF(B92<=0,0,MIN('Loan Calculator'!B4,B92*(1+'Loan Calculator'!B7))) -> 365.72 | D92: =IF(B92<=0,0,B92*'Loan Calculator'!B7) -> 20.443751 | E92: =IF(B92<=0,0,C92-D92) -> 345.27625 | F92: =IF(B92<=0,0,MAX(0,B92-E92)) -> 8513.6825 | G92: =G91+D92 -> 4904.2025
A93: 92 | B93: =MAX(0,F92) -> 8513.6825 | C93: =IF(B93<=0,0,MIN('Loan Calculator'!B4,B93*(1+'Loan Calculator'!B7))) -> 365.72 | D93: =IF(B93<=0,0,B93*'Loan Calculator'!B7) -> 19.64696 | E93: =IF(B93<=0,0,C93-D93) -> 346.07304 | F93: =IF(B93<=0,0,MAX(0,B93-E93)) -> 8167.6095 | G93: =G92+D93 -> 4923.8495
A94: 93 | B94: =MAX(0,F93) -> 8167.6095 | C94: =IF(B94<=0,0,MIN('Loan Calculator'!B4,B94*(1+'Loan Calculator'!B7))) -> 365.72 | D94: =IF(B94<=0,0,B94*'Loan Calculator'!B7) -> 18.84833 | E94: =IF(B94<=0,0,C94-D94) -> 346.87167 | F94: =IF(B94<=0,0,MAX(0,B94-E94)) -> 7820.7378 | G94: =G93+D94 -> 4942.6978
A95: 94 | B95: =MAX(0,F94) -> 7820.7378 | C95: =IF(B95<=0,0,MIN('Loan Calculator'!B4,B95*(1+'Loan Calculator'!B7))) -> 365.72 | D95: =IF(B95<=0,0,B95*'Loan Calculator'!B7) -> 18.047856 | E95: =IF(B95<=0,0,C95-D95) -> 347.67214 | F95: =IF(B95<=0,0,MAX(0,B95-E95)) -> 7473.0657 | G95: =G94+D95 -> 4960.7457
A96: 95 | B96: =MAX(0,F95) -> 7473.0657 | C96: =IF(B96<=0,0,MIN('Loan Calculator'!B4,B96*(1+'Loan Calculator'!B7))) -> 365.72 | D96: =IF(B96<=0,0,B96*'Loan Calculator'!B7) -> 17.245536 | E96: =IF(B96<=0,0,C96-D96) -> 348.47446 | F96: =IF(B96<=0,0,MAX(0,B96-E96)) -> 7124.5912 | G96: =G95+D96 -> 4977.9912
A97: 96 | B97: =MAX(0,F96) -> 7124.5912 | C97: =IF(B97<=0,0,MIN('Loan Calculator'!B4,B97*(1+'Loan Calculator'!B7))) -> 365.72 | D97: =IF(B97<=0,0,B97*'Loan Calculator'!B7) -> 16.441364 | E97: =IF(B97<=0,0,C97-D97) -> 349.27864 | F97: =IF(B97<=0,0,MAX(0,B97-E97)) -> 6775.3126 | G97: =G96+D97 -> 4994.4326
A98: 97 | B98: =MAX(0,F97) -> 6775.3126 | C98: =IF(B98<=0,0,MIN('Loan Calculator'!B4,B98*(1+'Loan Calculator'!B7))) -> 365.72 | D98: =IF(B98<=0,0,B98*'Loan Calculator'!B7) -> 15.635337 | E98: =IF(B98<=0,0,C98-D98) -> 350.08466 | F98: =IF(B98<=0,0,MAX(0,B98-E98)) -> 6425.2279 | G98: =G97+D98 -> 5010.0679
A99: 98 | B99: =MAX(0,F98) -> 6425.2279 | C99: =IF(B99<=0,0,MIN('Loan Calculator'!B4,B99*(1+'Loan Calculator'!B7))) -> 365.72 | D99: =IF(B99<=0,0,B99*'Loan Calculator'!B7) -> 14.827449 | E99: =IF(B99<=0,0,C99-D99) -> 350.89255 | F99: =IF(B99<=0,0,MAX(0,B99-E99)) -> 6074.3353 | G99: =G98+D99 -> 5024.8953
A100: 99 | B100: =MAX(0,F99) -> 6074.3353 | C100: =IF(B100<=0,0,MIN('Loan Calculator'!B4,B100*(1+'Loan Calculator'!B7))) -> 365.72 | D100: =IF(B100<=0,0,B100*'Loan Calculator'!B7) -> 14.017697 | E100: =IF(B100<=0,0,C100-D100) -> 351.7023 | F100: =IF(B100<=0,0,MAX(0,B100-E100)) -> 5722.633 | G100: =G99+D100 -> 5038.913
...
